<?xml version="1.0"?>
<blm id="bonjour" width="18" height="8">
	<header>
		<name>normanxxx</name>
		<description>Bonjourxxx</description>
		<creator>Blinkenpaint 2.4</creator>
		<author>norman</author>
		<width>18</width>
		<height>8</height>
		<loop>no</loop>
		<duration>38950</duration>
	</header>

	<frame ms="500">
		<row>000000000000000000</row>
		<row>000000000000000000</row>
		<row>000000000000000000</row>
		<row>000000000000000000</row>
		<row>000000000000000000</row>
		<row>000000000000000000</row>
		<row>000000000000000000</row>
		<row>000000000000000000</row>
	</frame>

	<frame ms="200">
		<row>000000000000000000</row>
		<row>000000000000000000</row>
		<row>000000000000000011</row>
		<row>000000000000000010</row>
		<row>000000000000000011</row>
		<row>000000000000000010</row>
		<row>000000000000000011</row>
		<row>000000000000000000</row>
	</frame>

	<frame ms="150">
		<row>000000000000000000</row>
		<row>000000000000000000</row>
		<row>000000000000000111</row>
		<row>000000000000000100</row>
		<row>000000000000000111</row>
		<row>000000000000000100</row>
		<row>000000000000000111</row>
		<row>000000000000000000</row>
	</frame>

	<frame ms="150">
		<row>000000000000000000</row>
		<row>000000000000000000</row>
		<row>000000000000001110</row>
		<row>000000000000001001</row>
		<row>000000000000001110</row>
		<row>000000000000001001</row>
		<row>000000000000001110</row>
		<row>000000000000000000</row>
	</frame>

	<frame ms="150">
		<row>000000000000000000</row>
		<row>000000000000000000</row>
		<row>000000000000011100</row>
		<row>000000000000010010</row>
		<row>000000000000011100</row>
		<row>000000000000010010</row>
		<row>000000000000011100</row>
		<row>000000000000000000</row>
	</frame>

	<frame ms="150">
		<row>000000000000000000</row>
		<row>000000000000000000</row>
		<row>000000000000111000</row>
		<row>000000000000100101</row>
		<row>000000000000111001</row>
		<row>000000000000100101</row>
		<row>000000000000111000</row>
		<row>000000000000000000</row>
	</frame>

	<frame ms="150">
		<row>000000000000000000</row>
		<row>000000000000000000</row>
		<row>000000000001110001</row>
		<row>000000000001001010</row>
		<row>000000000001110010</row>
		<row>000000000001001010</row>
		<row>000000000001110001</row>
		<row>000000000000000000</row>
	</frame>

	<frame ms="150">
		<row>000000000000000000</row>
		<row>000000000000000000</row>
		<row>000000000011100011</row>
		<row>000000000010010100</row>
		<row>000000000011100100</row>
		<row>000000000010010100</row>
		<row>000000000011100011</row>
		<row>000000000000000000</row>
	</frame>

	<frame ms="150">
		<row>000000000000000000</row>
		<row>000000000000000000</row>
		<row>000000000111000110</row>
		<row>000000000100101001</row>
		<row>000000000111001001</row>
		<row>000000000100101001</row>
		<row>000000000111000110</row>
		<row>000000000000000000</row>
	</frame>

	<frame ms="150">
		<row>000000000000000000</row>
		<row>000000000000000000</row>
		<row>000000001110001100</row>
		<row>000000001001010010</row>
		<row>000000001110010010</row>
		<row>000000001001010010</row>
		<row>000000001110001100</row>
		<row>000000000000000000</row>
	</frame>

	<frame ms="150">
		<row>000000000000000000</row>
		<row>000000000000000000</row>
		<row>000000011100011001</row>
		<row>000000010010100101</row>
		<row>000000011100100101</row>
		<row>000000010010100101</row>
		<row>000000011100011001</row>
		<row>000000000000000000</row>
	</frame>

	<frame ms="150">
		<row>000000000000000000</row>
		<row>000000000000000000</row>
		<row>000000111000110010</row>
		<row>000000100101001011</row>
		<row>000000111001001010</row>
		<row>000000100101001010</row>
		<row>000000111000110010</row>
		<row>000000000000000000</row>
	</frame>

	<frame ms="150">
		<row>000000000000000000</row>
		<row>000000000000000000</row>
		<row>000001110001100100</row>
		<row>000001001010010110</row>
		<row>000001110010010101</row>
		<row>000001001010010100</row>
		<row>000001110001100100</row>
		<row>000000000000000000</row>
	</frame>

	<frame ms="150">
		<row>000000000000000000</row>
		<row>000000000000000000</row>
		<row>000011100011001000</row>
		<row>000010010100101100</row>
		<row>000011100100101010</row>
		<row>000010010100101001</row>
		<row>000011100011001000</row>
		<row>000000000000000000</row>
	</frame>

	<frame ms="150">
		<row>000000000000000000</row>
		<row>000000000000000000</row>
		<row>000111000110010001</row>
		<row>000100101001011001</row>
		<row>000111001001010101</row>
		<row>000100101001010011</row>
		<row>000111000110010001</row>
		<row>000000000000000000</row>
	</frame>

	<frame ms="500">
		<row>000000000000000000</row>
		<row>000000000000000000</row>
		<row>001110001100100010</row>
		<row>001001010010110010</row>
		<row>001110010010101010</row>
		<row>001001010010100110</row>
		<row>001110001100100010</row>
		<row>000000000000000000</row>
	</frame>

	<frame ms="1000">
		<row>000000000000000000</row>
		<row>000000000000000000</row>
		<row>001110011001011100</row>
		<row>010000100101010010</row>
		<row>001100100101011100</row>
		<row>000010100101010100</row>
		<row>011100011001010010</row>
		<row>000000000000000000</row>
	</frame>

	<frame ms="800">
		<row>000000000000000000</row>
		<row>000000000000000000</row>
		<row>000000000000000000</row>
		<row>000000000000000000</row>
		<row>000000000000000000</row>
		<row>000000000000000000</row>
		<row>000000000000000000</row>
		<row>000000000000000000</row>
	</frame>

	<frame ms="800">
		<row>000000000000000000</row>
		<row>000001000000000000</row>
		<row>011010111001101110</row>
		<row>100000100010000100</row>
		<row>100000110001000100</row>
		<row>100000100000100100</row>
		<row>011000111011000100</row>
		<row>000000000000000000</row>
	</frame>

	<frame ms="500">
		<row>000000000000000000</row>
		<row>000000000000000000</row>
		<row>001000100110011100</row>
		<row>001100101001010010</row>
		<row>001010101001011100</row>
		<row>001001101001010100</row>
		<row>001000100110010010</row>
		<row>000000000000000000</row>
	</frame>

	<frame ms="200">
		<row>000000000000000000</row>
		<row>000000000000000000</row>
		<row>100010011001110010</row>
		<row>110010100101001011</row>
		<row>101010100101110010</row>
		<row>100110100101010010</row>
		<row>100010011001001010</row>
		<row>000000000000000000</row>
	</frame>

	<frame ms="200">
		<row>000000000000000000</row>
		<row>000000000000000000</row>
		<row>001001100111100100</row>
		<row>001010010100010110</row>
		<row>101010010111100101</row>
		<row>011010010100100100</row>
		<row>001001100100010100</row>
		<row>000000000000000000</row>
	</frame>

	<frame ms="200">
		<row>000000000000000000</row>
		<row>000000000000000000</row>
		<row>100110011100100010</row>
		<row>101001010010110110</row>
		<row>101001011100101010</row>
		<row>101001010100100010</row>
		<row>100110010010100010</row>
		<row>000000000000000000</row>
	</frame>

	<frame ms="200">
		<row>000000000000000000</row>
		<row>000000000000000000</row>
		<row>001100111001000100</row>
		<row>010010100101101101</row>
		<row>010010111001010101</row>
		<row>010010101001000101</row>
		<row>001100100101000101</row>
		<row>000000000000000000</row>
	</frame>

	<frame ms="200">
		<row>000000000000000000</row>
		<row>000000000000000000</row>
		<row>110011100100010011</row>
		<row>001010010110110100</row>
		<row>001011100101010100</row>
		<row>001010100100010111</row>
		<row>110010010100010100</row>
		<row>000000000000000000</row>
	</frame>

	<frame ms="200">
		<row>000000000000000000</row>
		<row>000000000000000000</row>
		<row>001111001000100110</row>
		<row>101000101101101001</row>
		<row>101111001010101001</row>
		<row>101001001000101111</row>
		<row>001000101000101001</row>
		<row>000000000000000000</row>
	</frame>

	<frame ms="200">
		<row>000000000000000000</row>
		<row>000000000000000000</row>
		<row>011100100010011001</row>
		<row>010010110110100101</row>
		<row>011100101010100101</row>
		<row>010100100010111101</row>
		<row>010010100010100101</row>
		<row>000000000000000000</row>
	</frame>

	<frame ms="200">
		<row>000000000000000000</row>
		<row>000000000000000000</row>
		<row>110010001001100100</row>
		<row>001011011010010110</row>
		<row>110010101010010101</row>
		<row>010010001011110100</row>
		<row>001010001010010100</row>
		<row>000000000000000000</row>
	</frame>

	<frame ms="200">
		<row>000000000000000000</row>
		<row>000000000000000000</row>
		<row>001000100110010001</row>
		<row>101101101001011001</row>
		<row>001010101001010101</row>
		<row>001000101111010011</row>
		<row>101000101001010011</row>
		<row>000000000000000000</row>
	</frame>

	<frame ms="500">
		<row>000000000000000000</row>
		<row>000000000000000000</row>
		<row>100010011001000100</row>
		<row>110110100101100100</row>
		<row>101010100101010100</row>
		<row>100010111101001100</row>
		<row>100010100101000100</row>
		<row>000000000000000000</row>
	</frame>

	<frame ms="900">
		<row>000000000000000000</row>
		<row>000001000000100000</row>
		<row>000010100001010000</row>
		<row>000000000000000000</row>
		<row>000100000000001000</row>
		<row>000111111111111000</row>
		<row>000000000000000000</row>
		<row>000000000000000000</row>
	</frame>

	<frame ms="200">
		<row>000000000000000000</row>
		<row>000000000000000000</row>
		<row>000000000000000000</row>
		<row>000000000000000000</row>
		<row>000000000000000000</row>
		<row>000000000000000000</row>
		<row>000000000000000000</row>
		<row>000000000000000000</row>
	</frame>

	<frame ms="500">
		<row>000000000000000000</row>
		<row>000000000000000000</row>
		<row>001100011001110000</row>
		<row>001110111011011000</row>
		<row>001101011011011000</row>
		<row>001100011011111000</row>
		<row>001100011011011000</row>
		<row>000000000000000000</row>
	</frame>

	<frame ms="500">
		<row>000000000000000000</row>
		<row>000000000000000000</row>
		<row>011100100100010101</row>
		<row>010001010110110101</row>
		<row>011001010101010101</row>
		<row>010001110100010101</row>
		<row>010001010100010101</row>
		<row>000000000000000000</row>
	</frame>

	<frame ms="200">
		<row>000000000000000000</row>
		<row>000000000000000000</row>
		<row>111001001000101010</row>
		<row>100010101101101010</row>
		<row>110010101010101010</row>
		<row>100011101000101010</row>
		<row>100010101000101011</row>
		<row>000000000000000000</row>
	</frame>

	<frame ms="200">
		<row>000000000000000000</row>
		<row>000000000000000000</row>
		<row>110010010001010100</row>
		<row>000101011011010100</row>
		<row>100101010101010100</row>
		<row>000111010001010100</row>
		<row>000101010001010111</row>
		<row>000000000000000000</row>
	</frame>

	<frame ms="200">
		<row>000000000000000000</row>
		<row>000000000000000000</row>
		<row>100100100010101000</row>
		<row>001010110110101000</row>
		<row>001010101010101000</row>
		<row>001110100010101000</row>
		<row>001010100010101110</row>
		<row>000000000000000000</row>
	</frame>

	<frame ms="200">
		<row>000000000000000000</row>
		<row>000000000000000000</row>
		<row>001001000101010001</row>
		<row>010101101101010001</row>
		<row>010101010101010001</row>
		<row>011101000101010001</row>
		<row>010101000101011101</row>
		<row>000000000000000000</row>
	</frame>

	<frame ms="200">
		<row>000000000000000000</row>
		<row>000000000000000000</row>
		<row>010010001010100010</row>
		<row>101011011010100010</row>
		<row>101010101010100010</row>
		<row>111010001010100010</row>
		<row>101010001010111011</row>
		<row>000000000000000000</row>
	</frame>

	<frame ms="200">
		<row>000000000000000000</row>
		<row>000000000000000000</row>
		<row>100100010101000100</row>
		<row>010110110101000100</row>
		<row>010101010101000100</row>
		<row>110100010101000100</row>
		<row>010100010101110111</row>
		<row>000000000000000000</row>
	</frame>

	<frame ms="200">
		<row>000000000000000000</row>
		<row>000000000000000000</row>
		<row>001000101010001000</row>
		<row>101101101010001000</row>
		<row>101010101010001000</row>
		<row>101000101010001000</row>
		<row>101000101011101110</row>
		<row>000000000000000000</row>
	</frame>

	<frame ms="200">
		<row>000000000000000000</row>
		<row>000000000000000000</row>
		<row>010001010100010001</row>
		<row>011011010100010001</row>
		<row>010101010100010001</row>
		<row>010001010100010001</row>
		<row>010001010111011101</row>
		<row>000000000000000000</row>
	</frame>

	<frame ms="200">
		<row>000000000000000000</row>
		<row>000000000000000000</row>
		<row>100010101000100010</row>
		<row>110110101000100010</row>
		<row>101010101000100010</row>
		<row>100010101000100010</row>
		<row>100010101110111010</row>
		<row>000000000000000000</row>
	</frame>

	<frame ms="200">
		<row>000000000000000000</row>
		<row>000000000000000000</row>
		<row>000101010001000101</row>
		<row>101101010001000101</row>
		<row>010101010001000101</row>
		<row>000101010001000101</row>
		<row>000101011101110101</row>
		<row>000000000000000000</row>
	</frame>

	<frame ms="200">
		<row>000000000000000000</row>
		<row>000000000000000000</row>
		<row>001010100010001011</row>
		<row>011010100010001010</row>
		<row>101010100010001011</row>
		<row>001010100010001010</row>
		<row>001010111011101011</row>
		<row>000000000000000000</row>
	</frame>

	<frame ms="200">
		<row>000000000000000000</row>
		<row>000000000000000000</row>
		<row>010101000100010111</row>
		<row>110101000100010100</row>
		<row>010101000100010110</row>
		<row>010101000100010100</row>
		<row>010101110111010111</row>
		<row>000000000000000000</row>
	</frame>

	<frame ms="500">
		<row>000000000000000000</row>
		<row>000000000000000000</row>
		<row>101010001000101110</row>
		<row>101010001000101000</row>
		<row>101010001000101100</row>
		<row>101010001000101000</row>
		<row>101011101110101110</row>
		<row>000000000000000000</row>
	</frame>

	<frame ms="500">
		<row>000000000000000000</row>
		<row>000000000001100000</row>
		<row>000111111011110000</row>
		<row>000110001011110000</row>
		<row>000111111001100000</row>
		<row>000110000001100000</row>
		<row>000111111001110000</row>
		<row>000000000000000000</row>
	</frame>

	<frame ms="800">
		<row>000000000000000000</row>
		<row>000000000000000000</row>
		<row>001101101110100000</row>
		<row>001010101010100000</row>
		<row>001000101110100000</row>
		<row>000000000000000000</row>
		<row>000000000000000000</row>
		<row>000000000000000000</row>
	</frame>

	<frame ms="200">
		<row>000000000000000000</row>
		<row>000000000000000000</row>
		<row>000000000000000000</row>
		<row>000000000000000000</row>
		<row>000000000000000000</row>
		<row>000000000000000000</row>
		<row>000000000000000000</row>
		<row>000000000000000000</row>
	</frame>

	<frame ms="500">
		<row>000000000000000000</row>
		<row>000000000000000000</row>
		<row>010101110101011100</row>
		<row>010101010101010000</row>
		<row>010101010101000100</row>
		<row>001001110111011100</row>
		<row>000000000000000000</row>
		<row>000000000000000000</row>
	</frame>

	<frame ms="400">
		<row>000000000000000000</row>
		<row>000000000000000000</row>
		<row>011110111101001010</row>
		<row>010000100101001010</row>
		<row>001100100101001011</row>
		<row>000010100101001010</row>
		<row>011110111101111010</row>
		<row>000000000000000000</row>
	</frame>

	<frame ms="150">
		<row>000000000000000000</row>
		<row>000000000000000000</row>
		<row>111101111010010100</row>
		<row>100001001010010100</row>
		<row>011001001010010111</row>
		<row>000101001010010100</row>
		<row>111101111011110100</row>
		<row>000000000000000000</row>
	</frame>

	<frame ms="150">
		<row>000000000000000000</row>
		<row>000000000000000000</row>
		<row>111011110100101001</row>
		<row>000010010100101001</row>
		<row>110010010100101111</row>
		<row>001010010100101001</row>
		<row>111011110111101001</row>
		<row>000000000000000000</row>
	</frame>

	<frame ms="150">
		<row>000000000000000000</row>
		<row>000000000000000000</row>
		<row>110111101001010010</row>
		<row>000100101001010010</row>
		<row>100100101001011110</row>
		<row>010100101001010010</row>
		<row>110111101111010010</row>
		<row>000000000000000000</row>
	</frame>

	<frame ms="150">
		<row>000000000000000000</row>
		<row>000000000000000000</row>
		<row>101111010010100100</row>
		<row>001001010010100101</row>
		<row>001001010010111101</row>
		<row>101001010010100101</row>
		<row>101111011110100100</row>
		<row>000000000000000000</row>
	</frame>

	<frame ms="150">
		<row>000000000000000000</row>
		<row>000000000000000000</row>
		<row>011110100101001001</row>
		<row>010010100101001010</row>
		<row>010010100101111011</row>
		<row>010010100101001010</row>
		<row>011110111101001010</row>
		<row>000000000000000000</row>
	</frame>

	<frame ms="150">
		<row>000000000000000000</row>
		<row>000000000000000000</row>
		<row>111101001010010011</row>
		<row>100101001010010100</row>
		<row>100101001011110111</row>
		<row>100101001010010100</row>
		<row>111101111010010100</row>
		<row>000000000000000000</row>
	</frame>

	<frame ms="150">
		<row>000000000000000000</row>
		<row>000000000000000000</row>
		<row>111010010100100110</row>
		<row>001010010100101001</row>
		<row>001010010111101111</row>
		<row>001010010100101001</row>
		<row>111011110100101001</row>
		<row>000000000000000000</row>
	</frame>

	<frame ms="150">
		<row>000000000000000000</row>
		<row>000000000000000000</row>
		<row>110100101001001100</row>
		<row>010100101001010010</row>
		<row>010100101111011110</row>
		<row>010100101001010010</row>
		<row>110111101001010010</row>
		<row>000000000000000000</row>
	</frame>

	<frame ms="150">
		<row>000000000000000000</row>
		<row>000000000000000000</row>
		<row>101001010010011001</row>
		<row>101001010010100101</row>
		<row>101001011110111101</row>
		<row>101001010010100101</row>
		<row>101111010010100101</row>
		<row>000000000000000000</row>
	</frame>

	<frame ms="150">
		<row>000000000000000000</row>
		<row>000000000000000000</row>
		<row>010010100100110010</row>
		<row>010010100101001010</row>
		<row>010010111101111010</row>
		<row>010010100101001010</row>
		<row>011110100101001010</row>
		<row>000000000000000000</row>
	</frame>

	<frame ms="150">
		<row>000000000000000000</row>
		<row>000000000000000000</row>
		<row>100101001001100101</row>
		<row>100101001010010100</row>
		<row>100101111011110100</row>
		<row>100101001010010100</row>
		<row>111101001010010100</row>
		<row>000000000000000000</row>
	</frame>

	<frame ms="150">
		<row>000000000000000000</row>
		<row>000000000000000000</row>
		<row>001010010011001011</row>
		<row>001010010100101001</row>
		<row>001011110111101001</row>
		<row>001010010100101001</row>
		<row>111010010100101001</row>
		<row>000000000000000000</row>
	</frame>

	<frame ms="150">
		<row>000000000000000000</row>
		<row>000000000000000000</row>
		<row>010100100110010111</row>
		<row>010100101001010010</row>
		<row>010111101111010010</row>
		<row>010100101001010010</row>
		<row>110100101001010010</row>
		<row>000000000000000000</row>
	</frame>

	<frame ms="150">
		<row>000000000000000000</row>
		<row>000000000000000000</row>
		<row>101001001100101110</row>
		<row>101001010010100100</row>
		<row>101111011110100100</row>
		<row>101001010010100100</row>
		<row>101001010010100100</row>
		<row>000000000000000000</row>
	</frame>

	<frame ms="150">
		<row>000000000000000000</row>
		<row>000000000000000000</row>
		<row>010010011001011101</row>
		<row>010010100101001001</row>
		<row>011110111101001001</row>
		<row>010010100101001001</row>
		<row>010010100101001001</row>
		<row>000000000000000000</row>
	</frame>

	<frame ms="150">
		<row>000000000000000000</row>
		<row>000000000000000000</row>
		<row>100100110010111011</row>
		<row>100101001010010010</row>
		<row>111101111010010011</row>
		<row>100101001010010010</row>
		<row>100101001010010011</row>
		<row>000000000000000000</row>
	</frame>

	<frame ms="150">
		<row>000000000000000000</row>
		<row>000000000000000000</row>
		<row>001001100101110111</row>
		<row>001010010100100100</row>
		<row>111011110100100110</row>
		<row>001010010100100100</row>
		<row>001010010100100111</row>
		<row>000000000000000000</row>
	</frame>

	<frame ms="500">
		<row>000000000000000000</row>
		<row>000000000000000000</row>
		<row>010011001011101110</row>
		<row>010100101001001000</row>
		<row>110111101001001100</row>
		<row>010100101001001000</row>
		<row>010100101001001110</row>
		<row>000000000000000000</row>
	</frame>

	<frame ms="750">
		<row>000000000000000000</row>
		<row>000000000000000000</row>
		<row>000000000000000000</row>
		<row>001100110110011000</row>
		<row>001100110111011000</row>
		<row>001100110110111000</row>
		<row>000111100110011000</row>
		<row>000000000000000000</row>
	</frame>

	<frame ms="400">
		<row>000000000000000000</row>
		<row>000100000000000000</row>
		<row>000000000000000000</row>
		<row>000101110101011101</row>
		<row>000101010111011001</row>
		<row>000101110001011101</row>
		<row>001100000011000000</row>
		<row>000000000000000000</row>
	</frame>

	<frame ms="150">
		<row>000000000000000000</row>
		<row>001000000000000000</row>
		<row>000000000000000000</row>
		<row>001011101010111010</row>
		<row>001010101110110010</row>
		<row>001011100010111011</row>
		<row>011000000110000000</row>
		<row>000000000000000000</row>
	</frame>

	<frame ms="150">
		<row>000000000000000000</row>
		<row>010000000000000000</row>
		<row>000000000000000000</row>
		<row>010111010101110101</row>
		<row>010101011101100101</row>
		<row>010111000101110111</row>
		<row>110000001100000000</row>
		<row>000000000000000000</row>
	</frame>

	<frame ms="150">
		<row>000000000000000000</row>
		<row>100000000000000000</row>
		<row>000000000000000000</row>
		<row>101110101011101010</row>
		<row>101010111011001010</row>
		<row>101110001011101110</row>
		<row>100000011000000000</row>
		<row>000000000000000000</row>
	</frame>

	<frame ms="150">
		<row>000000000000000000</row>
		<row>000000000000000000</row>
		<row>000000000000000000</row>
		<row>011101010111010101</row>
		<row>010101110110010100</row>
		<row>011100010111011101</row>
		<row>000000110000000000</row>
		<row>000000000000000000</row>
	</frame>

	<frame ms="150">
		<row>000000000000000000</row>
		<row>000000000000000000</row>
		<row>000000000000000000</row>
		<row>111010101110101010</row>
		<row>101011101100101001</row>
		<row>111000101110111010</row>
		<row>000001100000000000</row>
		<row>000000000000000000</row>
	</frame>

	<frame ms="150">
		<row>000000000000000000</row>
		<row>000000000000000000</row>
		<row>000000000000000000</row>
		<row>110101011101010101</row>
		<row>010111011001010010</row>
		<row>110001011101110101</row>
		<row>000011000000000000</row>
		<row>000000000000000000</row>
	</frame>

	<frame ms="750">
		<row>000000000000000000</row>
		<row>000000000000000000</row>
		<row>000000000000000000</row>
		<row>101010111010101010</row>
		<row>101110110010100100</row>
		<row>100010111011101010</row>
		<row>000110000000000000</row>
		<row>000000000000000000</row>
	</frame>

	<frame ms="1200">
		<row>000000000000000000</row>
		<row>000000000000000000</row>
		<row>110011000001010110</row>
		<row>111011000000000110</row>
		<row>110111011101110110</row>
		<row>110011010101100110</row>
		<row>110011011101110111</row>
		<row>000000000000000000</row>
	</frame>

	<frame ms="700">
		<row>000000000000000000</row>
		<row>000000000000000000</row>
		<row>000000000001000000</row>
		<row>000111111001000000</row>
		<row>000100001011100000</row>
		<row>000111111001000000</row>
		<row>000100000001010000</row>
		<row>000111111001110000</row>
	</frame>

	<frame ms="750">
		<row>000000000000000000</row>
		<row>000000000000000000</row>
		<row>000000000000000000</row>
		<row>010010010100011100</row>
		<row>010010011010010100</row>
		<row>010010010010010000</row>
		<row>011110010010011100</row>
		<row>000000000000000000</row>
	</frame>

	<frame ms="500">
		<row>000000000000000000</row>
		<row>000000000000000000</row>
		<row>111000000000000000</row>
		<row>100100000000000000</row>
		<row>111001110101101011</row>
		<row>100101010110101101</row>
		<row>111101110100101001</row>
		<row>000000000000000000</row>
	</frame>

	<frame ms="200">
		<row>000000000000000000</row>
		<row>000000000000000000</row>
		<row>110000000000000000</row>
		<row>001000000000000000</row>
		<row>110011101011010110</row>
		<row>001010101101011010</row>
		<row>111011101001010010</row>
		<row>000000000000000000</row>
	</frame>

	<frame ms="200">
		<row>000000000000000000</row>
		<row>000000000000000000</row>
		<row>100000000000000000</row>
		<row>010000000000000000</row>
		<row>100111010110101101</row>
		<row>010101011010110101</row>
		<row>110111010010100101</row>
		<row>000000000000000000</row>
	</frame>

	<frame ms="200">
		<row>000000000000000000</row>
		<row>000000000000000000</row>
		<row>000000000000000000</row>
		<row>100000000000000000</row>
		<row>001110101101011011</row>
		<row>101010110101101011</row>
		<row>101110100101001011</row>
		<row>000000000000000000</row>
	</frame>

	<frame ms="200">
		<row>000000000000000000</row>
		<row>000000000000000000</row>
		<row>000000000000000000</row>
		<row>000000000000000000</row>
		<row>011101011010110111</row>
		<row>010101101011010110</row>
		<row>011101001010010111</row>
		<row>000000000000000000</row>
	</frame>

	<frame ms="750">
		<row>000000000000000000</row>
		<row>000000000000000000</row>
		<row>000000000000000000</row>
		<row>000000000000000000</row>
		<row>111010110101101110</row>
		<row>101011010110101100</row>
		<row>111010010100101110</row>
		<row>000000000000000000</row>
	</frame>

	<frame ms="400">
		<row>000000000000000000</row>
		<row>000000000000000001</row>
		<row>000000000000000010</row>
		<row>011001001010010111</row>
		<row>100101101011010100</row>
		<row>111101011010110110</row>
		<row>100101001010010100</row>
		<row>100101001010010111</row>
	</frame>

	<frame ms="200">
		<row>000000000000000000</row>
		<row>000000000000000010</row>
		<row>000000000000000100</row>
		<row>110010010100101110</row>
		<row>001011010110101000</row>
		<row>111010110101101100</row>
		<row>001010010100101000</row>
		<row>001010010100101110</row>
	</frame>

	<frame ms="200">
		<row>000000000000000000</row>
		<row>000000000000000100</row>
		<row>000000000000001000</row>
		<row>100100101001011101</row>
		<row>010110101101010001</row>
		<row>110101101011011001</row>
		<row>010100101001010001</row>
		<row>010100101001011101</row>
	</frame>

	<frame ms="200">
		<row>000000000000000000</row>
		<row>000000000000001000</row>
		<row>000000000000010000</row>
		<row>001001010010111011</row>
		<row>101101011010100010</row>
		<row>101011010110110011</row>
		<row>101001010010100010</row>
		<row>101001010010111011</row>
	</frame>

	<frame ms="200">
		<row>000000000000000000</row>
		<row>000000000000010000</row>
		<row>000000000000100000</row>
		<row>010010100101110111</row>
		<row>011010110101000100</row>
		<row>010110101101100110</row>
		<row>010010100101000100</row>
		<row>010010100101110111</row>
	</frame>

	<frame ms="650">
		<row>000000000000000000</row>
		<row>000000000000100000</row>
		<row>000000000001000000</row>
		<row>100101001011101110</row>
		<row>110101101010001000</row>
		<row>101101011011001100</row>
		<row>100101001010001000</row>
		<row>100101001011101110</row>
	</frame>

	<frame ms="100">
		<row>000000000000000000</row>
		<row>000000000000000000</row>
		<row>000000000000000000</row>
		<row>000000000000000000</row>
		<row>000000000000000000</row>
		<row>000000000000000000</row>
		<row>000000000000000000</row>
		<row>000000000000000100</row>
	</frame>

	<frame ms="150">
		<row>000000000000000000</row>
		<row>000000000000000000</row>
		<row>000000000000000000</row>
		<row>000000000000000000</row>
		<row>000000000000000000</row>
		<row>000000000000001000</row>
		<row>000000000000000000</row>
		<row>000000000000000000</row>
	</frame>

	<frame ms="150">
		<row>000000000000000000</row>
		<row>000000000000000000</row>
		<row>000000000000000000</row>
		<row>000000000000010000</row>
		<row>000000000000000000</row>
		<row>000000000000000000</row>
		<row>000000000000000000</row>
		<row>000000000000000000</row>
	</frame>

	<frame ms="150">
		<row>000000000000000000</row>
		<row>000000000000000000</row>
		<row>000000000000100000</row>
		<row>000000000000000000</row>
		<row>000000000000000000</row>
		<row>000000000000000000</row>
		<row>000000000000000000</row>
		<row>000000000000000000</row>
	</frame>

	<frame ms="150">
		<row>000000000000000000</row>
		<row>000000000001000000</row>
		<row>000000000000000000</row>
		<row>000000000000000000</row>
		<row>000000000000000000</row>
		<row>000000000000000000</row>
		<row>000000000000000000</row>
		<row>000000000000000000</row>
	</frame>

	<frame ms="250">
		<row>000000000000000000</row>
		<row>000000000010000000</row>
		<row>000000000000000000</row>
		<row>000000000000000000</row>
		<row>000000000000000000</row>
		<row>000000000000000000</row>
		<row>000000000000000000</row>
		<row>000000000000000000</row>
	</frame>

	<frame ms="50">
		<row>000000000010000000</row>
		<row>000000000111000000</row>
		<row>000000000010000000</row>
		<row>000000000000000000</row>
		<row>000000000000000000</row>
		<row>000000000000000000</row>
		<row>000000000000000000</row>
		<row>000000000000000000</row>
	</frame>

	<frame ms="50">
		<row>000000000101000000</row>
		<row>000000011010110000</row>
		<row>000000000101000000</row>
		<row>000000001000100000</row>
		<row>000000000000000000</row>
		<row>000000000000000000</row>
		<row>000000000000000000</row>
		<row>000000000000000000</row>
	</frame>

	<frame ms="100">
		<row>000000000101000000</row>
		<row>000000011010110000</row>
		<row>000000100101001000</row>
		<row>000000001000100000</row>
		<row>000000010000010000</row>
		<row>000000000000000000</row>
		<row>000000000000000000</row>
		<row>000000000000000000</row>
	</frame>

	<frame ms="100">
		<row>000010000101000010</row>
		<row>000000011010110000</row>
		<row>000000100101001000</row>
		<row>000001001000100100</row>
		<row>000000010000010000</row>
		<row>000000010000010000</row>
		<row>000000000000000000</row>
		<row>000000000000000000</row>
	</frame>

	<frame ms="100">
		<row>000010000101000010</row>
		<row>000100011010110001</row>
		<row>000000100101001000</row>
		<row>000001001000100100</row>
		<row>000010010000010010</row>
		<row>000000010000010000</row>
		<row>000000010000010000</row>
		<row>000000000000000000</row>
	</frame>

	<frame ms="100">
		<row>000010000101000010</row>
		<row>000100011010110001</row>
		<row>001000100101001000</row>
		<row>000001001000100100</row>
		<row>000010010000010010</row>
		<row>000010010000010010</row>
		<row>000000010000010000</row>
		<row>000000010000010000</row>
	</frame>

	<frame ms="100">
		<row>000010000101000010</row>
		<row>000100011010110001</row>
		<row>001000100101001000</row>
		<row>010001001000100100</row>
		<row>000010010000010010</row>
		<row>000010010000010010</row>
		<row>000010010000010010</row>
		<row>000000010000010000</row>
	</frame>

	<frame ms="100">
		<row>000010000101000010</row>
		<row>000100011010110001</row>
		<row>001000100101001000</row>
		<row>010001001000100100</row>
		<row>010010010000010010</row>
		<row>000010010000010010</row>
		<row>000010010000010010</row>
		<row>000010010000010010</row>
	</frame>

	<frame ms="150">
		<row>000001001000100100</row>
		<row>000010000101000010</row>
		<row>000100011010110001</row>
		<row>001000100101001000</row>
		<row>010001001000100100</row>
		<row>010010010000010010</row>
		<row>010010010000010010</row>
		<row>000010010000010010</row>
	</frame>

	<frame ms="150">
		<row>000000110000011000</row>
		<row>000001001000100100</row>
		<row>000010000101000010</row>
		<row>000100011000110001</row>
		<row>001000100101001000</row>
		<row>010001001000100100</row>
		<row>010010010000010010</row>
		<row>010010010000010010</row>
	</frame>

	<frame ms="150">
		<row>000000000000000000</row>
		<row>000000110000011000</row>
		<row>000001001000100100</row>
		<row>000010000000000010</row>
		<row>000100010000010001</row>
		<row>001000100000001000</row>
		<row>010001001000100100</row>
		<row>010010010000010010</row>
	</frame>

	<frame ms="150">
		<row>000000000000000000</row>
		<row>000000000000000000</row>
		<row>000000110000011000</row>
		<row>000001000000000100</row>
		<row>000010000000000010</row>
		<row>000100000000000001</row>
		<row>001000100000001000</row>
		<row>010001000000000100</row>
	</frame>

	<frame ms="150">
		<row>000000000000000000</row>
		<row>000000000000000000</row>
		<row>000000000000000000</row>
		<row>000000100000001000</row>
		<row>000001000000000100</row>
		<row>000010000000000010</row>
		<row>000100000000000001</row>
		<row>001000000000000000</row>
	</frame>

	<frame ms="150">
		<row>000000000000000000</row>
		<row>000000000000000000</row>
		<row>000000000000000000</row>
		<row>000000000000000000</row>
		<row>000000000000000000</row>
		<row>000001000000000100</row>
		<row>000010000000000010</row>
		<row>000100000000000001</row>
	</frame>

	<frame ms="150">
		<row>000000000000000000</row>
		<row>000000000000000000</row>
		<row>000000000000000000</row>
		<row>000000000000000000</row>
		<row>000000000000000000</row>
		<row>000000000000000000</row>
		<row>000000000000000000</row>
		<row>000010000000000010</row>
	</frame>

	<frame ms="150">
		<row>100001000000000100</row>
		<row>000000000000000000</row>
		<row>000000000000000000</row>
		<row>000000000000000000</row>
		<row>000000000000000000</row>
		<row>000000000000000000</row>
		<row>000000000000000000</row>
		<row>000000000000000000</row>
	</frame>

	<frame ms="150">
		<row>000000100100000010</row>
		<row>010010000000001000</row>
		<row>000000000000000000</row>
		<row>000000000000000000</row>
		<row>000000000000000000</row>
		<row>000000000000000000</row>
		<row>000000000000000000</row>
		<row>000000000000000000</row>
	</frame>

	<frame ms="150">
		<row>010000000010010001</row>
		<row>000001001000000100</row>
		<row>001100000000000100</row>
		<row>000000000000000000</row>
		<row>000000000000000000</row>
		<row>000000000000000000</row>
		<row>000000000000000000</row>
		<row>000000000000000000</row>
	</frame>

	<frame ms="150">
		<row>000000100001000100</row>
		<row>001000000100100001</row>
		<row>000000101000000010</row>
		<row>001001000000010000</row>
		<row>000000000000000000</row>
		<row>000000000000000000</row>
		<row>000000000000000000</row>
		<row>000000000000000000</row>
	</frame>

	<frame ms="150">
		<row>010000100000010000</row>
		<row>000000010010000010</row>
		<row>000010000010010100</row>
		<row>000010000100000001</row>
		<row>010001000000001000</row>
		<row>000000000000000000</row>
		<row>000000000000000000</row>
		<row>000000000000000000</row>
	</frame>

	<frame ms="150">
		<row>000100001000100000</row>
		<row>001001000000001000</row>
		<row>000000100001000100</row>
		<row>000100000100100010</row>
		<row>000001000010000010</row>
		<row>100010000000010000</row>
		<row>000000000000000000</row>
		<row>000000000000000000</row>
	</frame>

	<frame ms="150">
		<row>000000100000010010</row>
		<row>000100000101000000</row>
		<row>010000100000001000</row>
		<row>000001000010001000</row>
		<row>001000000100010100</row>
		<row>000010000001000001</row>
		<row>100001000000001000</row>
		<row>000000000000000000</row>
	</frame>

	<frame ms="150">
		<row>100100000010000000</row>
		<row>000001000000001001</row>
		<row>000010000010100000</row>
		<row>100000010000010000</row>
		<row>000010000001000100</row>
		<row>001000001000101000</row>
		<row>000001000010000010</row>
		<row>100001000000001000</row>
	</frame>

	<frame ms="150">
		<row>000000010000100010</row>
		<row>010010000100000000</row>
		<row>000000100000000110</row>
		<row>000100000001010000</row>
		<row>010000100000001000</row>
		<row>000001000000100010</row>
		<row>000100010001000100</row>
		<row>100001100100001001</row>
	</frame>

	<frame ms="150">
		<row>010000000010000100</row>
		<row>000000100000010001</row>
		<row>100100001000000000</row>
		<row>000001000000000110</row>
		<row>000100000010001000</row>
		<row>001000010000010000</row>
		<row>000010000001000100</row>
		<row>101001101100101011</row>
	</frame>

	<frame ms="150">
		<row>001000001000001000</row>
		<row>100000000001000010</row>
		<row>000001000000001010</row>
		<row>011000000100000000</row>
		<row>000010000000001001</row>
		<row>000100000001010000</row>
		<row>010000001000001000</row>
		<row>101101101110101111</row>
	</frame>

	<frame ms="150">
		<row>010000000010000010</row>
		<row>000100010000010000</row>
		<row>010000000010000100</row>
		<row>000000100000010001</row>
		<row>100100001000000000</row>
		<row>000001000000000101</row>
		<row>000010000010100000</row>
		<row>111101111110111111</row>
	</frame>

	<frame ms="150">
		<row>000010010000010000</row>
		<row>001000000100000100</row>
		<row>000010100000100000</row>
		<row>001000000100001000</row>
		<row>000001000000100010</row>
		<row>010010000100000000</row>
		<row>000001000000100011</row>
		<row>111111111111111111</row>
	</frame>

	<frame ms="150">
		<row>001000000100000100</row>
		<row>000001100000100000</row>
		<row>010000001000000010</row>
		<row>000100010001000000</row>
		<row>010000000010010000</row>
		<row>000000100000010100</row>
		<row>100101000010100011</row>
		<row>111111111111111111</row>
	</frame>

	<frame ms="150">
		<row>000100010000010000</row>
		<row>010000000010000010</row>
		<row>000010010000010000</row>
		<row>001000000100000100</row>
		<row>000100100001000000</row>
		<row>001000000100100000</row>
		<row>100101010010101111</row>
		<row>111111111111111111</row>
	</frame>

	<frame ms="150">
		<row>010000000100000010</row>
		<row>000010100000100000</row>
		<row>001000000100000100</row>
		<row>000100100000100000</row>
		<row>010000000010000010</row>
		<row>000100010000100000</row>
		<row>110101011010111111</row>
		<row>111111111111111111</row>
	</frame>

	<frame ms="150">
		<row>000001000000100001</row>
		<row>001000001000000100</row>
		<row>000100010000000000</row>
		<row>010000000010001000</row>
		<row>000010010000010000</row>
		<row>001000000100000100</row>
		<row>111101111011111111</row>
		<row>111111111111111111</row>
	</frame>

	<frame ms="150">
		<row>010000000010000000</row>
		<row>000010000000010010</row>
		<row>010000000001000010</row>
		<row>000010101000000000</row>
		<row>001000000001010000</row>
		<row>000100001000100100</row>
		<row>111111111111111111</row>
		<row>111111111111111111</row>
	</frame>

	<frame ms="150">
		<row>000000100000000100</row>
		<row>001000000001000000</row>
		<row>000100000000001100</row>
		<row>001000000000100001</row>
		<row>000001010100000000</row>
		<row>010100001010101100</row>
		<row>111111111111111111</row>
		<row>111111111111111111</row>
	</frame>

	<frame ms="150">
		<row>000100000001000000</row>
		<row>000000010000001000</row>
		<row>000100000010000000</row>
		<row>001000000000010010</row>
		<row>000100000000010010</row>
		<row>010100111110101100</row>
		<row>111111111111111111</row>
		<row>111111111111111111</row>
	</frame>

	<frame ms="150">
		<row>000000100000000000</row>
		<row>001000000000100000</row>
		<row>000000100000000100</row>
		<row>000010000100000000</row>
		<row>010000000000001001</row>
		<row>010110111110111101</row>
		<row>111111111111111111</row>
		<row>111111111111111111</row>
	</frame>

	<frame ms="150">
		<row>000000000000100000</row>
		<row>000001000000000000</row>
		<row>010000000001000000</row>
		<row>000000010000000010</row>
		<row>000001000010000000</row>
		<row>110110111110111111</row>
		<row>111111111111111111</row>
		<row>111111111111111111</row>
	</frame>

	<frame ms="150">
		<row>000000000000000000</row>
		<row>000000000000010000</row>
		<row>000000100000000000</row>
		<row>001000000000100000</row>
		<row>000000001000000100</row>
		<row>110111111111111111</row>
		<row>111111111111111111</row>
		<row>111111111111111111</row>
	</frame>

	<frame ms="150">
		<row>000000000000000000</row>
		<row>000000000000000000</row>
		<row>000000000000001000</row>
		<row>000001000000000000</row>
		<row>010000000001000000</row>
		<row>110111111111111111</row>
		<row>111111111111111111</row>
		<row>111111111111111111</row>
	</frame>

	<frame ms="150">
		<row>000000000000000000</row>
		<row>000000000000000000</row>
		<row>000000000000000000</row>
		<row>000000000000000100</row>
		<row>000010000000000000</row>
		<row>111111111111111111</row>
		<row>111111111111111111</row>
		<row>111111111111111111</row>
	</frame>

	<frame ms="150">
		<row>000000000000000000</row>
		<row>000000000000000000</row>
		<row>000000000000000000</row>
		<row>000000000000000000</row>
		<row>000000000000001000</row>
		<row>111111111111111111</row>
		<row>111111111111111111</row>
		<row>111111111111111111</row>
	</frame>

	<frame ms="1000">
		<row>000000000000000000</row>
		<row>000000000000000000</row>
		<row>000000000000000000</row>
		<row>000000000000000000</row>
		<row>000000000000000000</row>
		<row>111111111111111111</row>
		<row>111111111111111111</row>
		<row>111111111111111111</row>
	</frame>

	<frame ms="1000">
		<row>000000000000000000</row>
		<row>000000000000000000</row>
		<row>000000000000000000</row>
		<row>000000000000000000</row>
		<row>000000000000000000</row>
		<row>000000000000000000</row>
		<row>000000000000000000</row>
		<row>000000000000000000</row>
	</frame>

	<frame ms="1000">
		<row>000000000000000000</row>
		<row>000000000000000000</row>
		<row>000000000000000000</row>
		<row>000000000000000000</row>
		<row>000000000000000000</row>
		<row>000000000000000000</row>
		<row>000000000000000000</row>
		<row>000000000000000000</row>
	</frame>

	<frame ms="1000">
		<row>001000000000000000</row>
		<row>000000000000000000</row>
		<row>000000000000000000</row>
		<row>000000000000000000</row>
		<row>000000000000000000</row>
		<row>000000000000000000</row>
		<row>000000000000000000</row>
		<row>000000000000000000</row>
	</frame>
</blm>
