<?xml version="1.0"?>
<blm id="stefan" width="18" height="8">
	<header>
		<name>stefan</name>
		<description></description>
		<creator>Blinkenpaint 2.4</creator>
		<author></author>
		<width>18</width>
		<height>8</height>
		<loop>no</loop>
		<duration>61100</duration>
	</header>

	<frame ms="200">
		<row>000000000000000000</row>
		<row>000000000000000001</row>
		<row>000000000000000001</row>
		<row>000000000000000001</row>
		<row>000000000000000001</row>
		<row>000000000000000001</row>
		<row>000000000000000001</row>
		<row>000000000000000000</row>
	</frame>

	<frame ms="200">
		<row>000000000000000000</row>
		<row>000000000000000011</row>
		<row>000000000000000011</row>
		<row>000000000000000011</row>
		<row>000000000000000011</row>
		<row>000000000000000011</row>
		<row>000000000000000011</row>
		<row>000000000000000000</row>
	</frame>

	<frame ms="200">
		<row>000000000000000000</row>
		<row>000000000000000110</row>
		<row>000000000000000110</row>
		<row>000000000000000110</row>
		<row>000000000000000110</row>
		<row>000000000000000110</row>
		<row>000000000000000110</row>
		<row>000000000000000000</row>
	</frame>

	<frame ms="200">
		<row>000000000000000000</row>
		<row>000000000000001100</row>
		<row>000000000000001100</row>
		<row>000000000000001100</row>
		<row>000000000000001100</row>
		<row>000000000000001100</row>
		<row>000000000000001100</row>
		<row>000000000000000000</row>
	</frame>

	<frame ms="200">
		<row>000000000000000000</row>
		<row>000000000000011001</row>
		<row>000000000000011001</row>
		<row>000000000000011001</row>
		<row>000000000000011001</row>
		<row>000000000000011001</row>
		<row>000000000000011001</row>
		<row>000000000000000000</row>
	</frame>

	<frame ms="200">
		<row>000000000000000000</row>
		<row>000000000000110011</row>
		<row>000000000000110011</row>
		<row>000000000000110011</row>
		<row>000000000000110011</row>
		<row>000000000000110011</row>
		<row>000000000000110011</row>
		<row>000000000000000000</row>
	</frame>

	<frame ms="200">
		<row>000000000000000000</row>
		<row>000000000001100110</row>
		<row>000000000001100110</row>
		<row>000000000001100111</row>
		<row>000000000001100111</row>
		<row>000000000001100110</row>
		<row>000000000001100110</row>
		<row>000000000000000000</row>
	</frame>

	<frame ms="200">
		<row>000000000000000000</row>
		<row>000000000011001100</row>
		<row>000000000011001100</row>
		<row>000000000011001111</row>
		<row>000000000011001111</row>
		<row>000000000011001100</row>
		<row>000000000011001100</row>
		<row>000000000000000000</row>
	</frame>

	<frame ms="200">
		<row>000000000000000000</row>
		<row>000000000110011001</row>
		<row>000000000110011001</row>
		<row>000000000110011111</row>
		<row>000000000110011111</row>
		<row>000000000110011001</row>
		<row>000000000110011001</row>
		<row>000000000000000000</row>
	</frame>

	<frame ms="200">
		<row>000000000000000000</row>
		<row>000000001100110011</row>
		<row>000000001100110011</row>
		<row>000000001100111111</row>
		<row>000000001100111111</row>
		<row>000000001100110011</row>
		<row>000000001100110011</row>
		<row>000000000000000000</row>
	</frame>

	<frame ms="200">
		<row>000000000000000000</row>
		<row>000000011001100110</row>
		<row>000000011001100110</row>
		<row>000000011001111110</row>
		<row>000000011001111110</row>
		<row>000000011001100110</row>
		<row>000000011001100110</row>
		<row>000000000000000000</row>
	</frame>

	<frame ms="200">
		<row>000000000000000000</row>
		<row>000000110011001100</row>
		<row>000000110011001100</row>
		<row>000000110011111100</row>
		<row>000000110011111100</row>
		<row>000000110011001100</row>
		<row>000000110011001100</row>
		<row>000000000000000000</row>
	</frame>

	<frame ms="200">
		<row>000000000000000000</row>
		<row>000001100110011001</row>
		<row>000001100110011001</row>
		<row>000001100111111001</row>
		<row>000001100111111001</row>
		<row>000001100110011001</row>
		<row>000001100110011001</row>
		<row>000000000000000000</row>
	</frame>

	<frame ms="200">
		<row>000000000000000000</row>
		<row>000011001100110011</row>
		<row>000011001100110011</row>
		<row>000011001111110011</row>
		<row>000011001111110011</row>
		<row>000011001100110011</row>
		<row>000011001100110011</row>
		<row>000000000000000000</row>
	</frame>

	<frame ms="200">
		<row>000000000000000000</row>
		<row>000110011001100111</row>
		<row>000110011001100110</row>
		<row>000110011111100111</row>
		<row>000110011111100111</row>
		<row>000110011001100110</row>
		<row>000110011001100110</row>
		<row>000000000000000000</row>
	</frame>

	<frame ms="200">
		<row>000000000000000000</row>
		<row>001100110011001111</row>
		<row>001100110011001100</row>
		<row>001100111111001111</row>
		<row>001100111111001110</row>
		<row>001100110011001101</row>
		<row>001100110011001100</row>
		<row>000000000000000000</row>
	</frame>

	<frame ms="200">
		<row>000000000000000000</row>
		<row>011001100110011110</row>
		<row>011001100110011001</row>
		<row>011001111110011110</row>
		<row>011001111110011100</row>
		<row>011001100110011010</row>
		<row>011001100110011001</row>
		<row>000000000000000000</row>
	</frame>

	<frame ms="200">
		<row>000000000000000000</row>
		<row>110011001100111100</row>
		<row>110011001100110010</row>
		<row>110011111100111100</row>
		<row>110011111100111000</row>
		<row>110011001100110100</row>
		<row>110011001100110010</row>
		<row>000000000000000000</row>
	</frame>

	<frame ms="200">
		<row>000000000000000000</row>
		<row>100110011001111000</row>
		<row>100110011001100100</row>
		<row>100111111001111000</row>
		<row>100111111001110000</row>
		<row>100110011001101000</row>
		<row>100110011001100100</row>
		<row>000000000000000000</row>
	</frame>

	<frame ms="200">
		<row>000000000000000000</row>
		<row>001100110011110000</row>
		<row>001100110011001000</row>
		<row>001111110011110000</row>
		<row>001111110011100000</row>
		<row>001100110011010000</row>
		<row>001100110011001000</row>
		<row>000000000000000000</row>
	</frame>

	<frame ms="200">
		<row>000000000000000000</row>
		<row>011001100111100000</row>
		<row>011001100110010000</row>
		<row>011111100111100000</row>
		<row>011111100111000000</row>
		<row>011001100110100000</row>
		<row>011001100110010000</row>
		<row>000000000000000000</row>
	</frame>

	<frame ms="200">
		<row>000000000000000000</row>
		<row>110011001111000000</row>
		<row>110011001100100000</row>
		<row>111111001111000000</row>
		<row>111111001110000000</row>
		<row>110011001101000000</row>
		<row>110011001100100000</row>
		<row>000000000000000000</row>
	</frame>

	<frame ms="200">
		<row>000000000000000000</row>
		<row>100110011110000001</row>
		<row>100110011001000001</row>
		<row>111110011110000001</row>
		<row>111110011100000001</row>
		<row>100110011010000001</row>
		<row>100110011001000001</row>
		<row>000000000000000000</row>
	</frame>

	<frame ms="200">
		<row>000000000000000000</row>
		<row>001100111100000011</row>
		<row>001100110010000011</row>
		<row>111100111100000011</row>
		<row>111100111000000011</row>
		<row>001100110100000011</row>
		<row>001100110010000011</row>
		<row>000000000000000000</row>
	</frame>

	<frame ms="200">
		<row>000000000000000000</row>
		<row>011001111000000110</row>
		<row>011001100100000110</row>
		<row>111001111000000110</row>
		<row>111001110000000110</row>
		<row>011001101000000111</row>
		<row>011001100100000111</row>
		<row>000000000000000000</row>
	</frame>

	<frame ms="200">
		<row>000000000000000000</row>
		<row>110011110000001100</row>
		<row>110011001000001100</row>
		<row>110011110000001100</row>
		<row>110011100000001100</row>
		<row>110011010000001111</row>
		<row>110011001000001111</row>
		<row>000000000000000000</row>
	</frame>

	<frame ms="200">
		<row>000000000000000000</row>
		<row>100111100000011000</row>
		<row>100110010000011000</row>
		<row>100111100000011000</row>
		<row>100111000000011000</row>
		<row>100110100000011111</row>
		<row>100110010000011111</row>
		<row>000000000000000000</row>
	</frame>

	<frame ms="200">
		<row>000000000000000000</row>
		<row>001111000000110000</row>
		<row>001100100000110000</row>
		<row>001111000000110000</row>
		<row>001110000000110000</row>
		<row>001101000000111111</row>
		<row>001100100000111111</row>
		<row>000000000000000000</row>
	</frame>

	<frame ms="200">
		<row>000000000000000000</row>
		<row>011110000001100000</row>
		<row>011001000001100000</row>
		<row>011110000001100000</row>
		<row>011100000001100000</row>
		<row>011010000001111110</row>
		<row>011001000001111110</row>
		<row>000000000000000000</row>
	</frame>

	<frame ms="200">
		<row>000000000000000000</row>
		<row>111100000011000000</row>
		<row>110010000011000000</row>
		<row>111100000011000000</row>
		<row>111000000011000000</row>
		<row>110100000011111100</row>
		<row>110010000011111100</row>
		<row>000000000000000000</row>
	</frame>

	<frame ms="200">
		<row>000000000000000000</row>
		<row>111000000110000001</row>
		<row>100100000110000001</row>
		<row>111000000110000001</row>
		<row>110000000110000001</row>
		<row>101000000111111001</row>
		<row>100100000111111001</row>
		<row>000000000000000000</row>
	</frame>

	<frame ms="200">
		<row>000000000000000000</row>
		<row>110000001100000011</row>
		<row>001000001100000011</row>
		<row>110000001100000011</row>
		<row>100000001100000011</row>
		<row>010000001111110011</row>
		<row>001000001111110011</row>
		<row>000000000000000000</row>
	</frame>

	<frame ms="200">
		<row>000000000000000000</row>
		<row>100000011000000110</row>
		<row>010000011000000110</row>
		<row>100000011000000110</row>
		<row>000000011000000110</row>
		<row>100000011111100110</row>
		<row>010000011111100110</row>
		<row>000000000000000000</row>
	</frame>

	<frame ms="200">
		<row>000000000000000000</row>
		<row>000000110000001100</row>
		<row>100000110000001100</row>
		<row>000000110000001100</row>
		<row>000000110000001100</row>
		<row>000000111111001100</row>
		<row>100000111111001100</row>
		<row>000000000000000000</row>
	</frame>

	<frame ms="200">
		<row>000000000000000000</row>
		<row>000001100000011001</row>
		<row>000001100000011001</row>
		<row>000001100000011001</row>
		<row>000001100000011001</row>
		<row>000001111110011001</row>
		<row>000001111110011001</row>
		<row>000000000000000000</row>
	</frame>

	<frame ms="200">
		<row>000000000000000000</row>
		<row>000011000000110011</row>
		<row>000011000000110011</row>
		<row>000011000000110011</row>
		<row>000011000000110011</row>
		<row>000011111100110011</row>
		<row>000011111100110011</row>
		<row>000000000000000000</row>
	</frame>

	<frame ms="200">
		<row>000000000000000000</row>
		<row>000110000001100111</row>
		<row>000110000001100110</row>
		<row>000110000001100111</row>
		<row>000110000001100111</row>
		<row>000111111001100110</row>
		<row>000111111001100111</row>
		<row>000000000000000000</row>
	</frame>

	<frame ms="200">
		<row>000000000000000000</row>
		<row>001100000011001111</row>
		<row>001100000011001100</row>
		<row>001100000011001111</row>
		<row>001100000011001111</row>
		<row>001111110011001100</row>
		<row>001111110011001111</row>
		<row>000000000000000000</row>
	</frame>

	<frame ms="200">
		<row>000000000000000000</row>
		<row>011000000110011111</row>
		<row>011000000110011000</row>
		<row>011000000110011111</row>
		<row>011000000110011111</row>
		<row>011111100110011000</row>
		<row>011111100110011111</row>
		<row>000000000000000000</row>
	</frame>

	<frame ms="200">
		<row>000000000000000000</row>
		<row>110000001100111111</row>
		<row>110000001100110000</row>
		<row>110000001100111111</row>
		<row>110000001100111111</row>
		<row>111111001100110000</row>
		<row>111111001100111111</row>
		<row>000000000000000000</row>
	</frame>

	<frame ms="200">
		<row>000000000000000000</row>
		<row>100000011001111110</row>
		<row>100000011001100000</row>
		<row>100000011001111110</row>
		<row>100000011001111110</row>
		<row>111110011001100000</row>
		<row>111110011001111110</row>
		<row>000000000000000000</row>
	</frame>

	<frame ms="200">
		<row>000000000000000000</row>
		<row>000000110011111100</row>
		<row>000000110011000000</row>
		<row>000000110011111100</row>
		<row>000000110011111100</row>
		<row>111100110011000000</row>
		<row>111100110011111100</row>
		<row>000000000000000000</row>
	</frame>

	<frame ms="200">
		<row>000000000000000000</row>
		<row>000001100111111001</row>
		<row>000001100110000001</row>
		<row>000001100111111001</row>
		<row>000001100111111001</row>
		<row>111001100110000001</row>
		<row>111001100111111001</row>
		<row>000000000000000000</row>
	</frame>

	<frame ms="200">
		<row>000000000000000000</row>
		<row>000011001111110011</row>
		<row>000011001100000011</row>
		<row>000011001111110011</row>
		<row>000011001111110011</row>
		<row>110011001100000011</row>
		<row>110011001111110011</row>
		<row>000000000000000000</row>
	</frame>

	<frame ms="200">
		<row>000000000000000000</row>
		<row>000110011111100111</row>
		<row>000110011000000110</row>
		<row>000110011111100111</row>
		<row>000110011111100111</row>
		<row>100110011000000110</row>
		<row>100110011111100111</row>
		<row>000000000000000000</row>
	</frame>

	<frame ms="200">
		<row>000000000000000000</row>
		<row>001100111111001111</row>
		<row>001100110000001100</row>
		<row>001100111111001111</row>
		<row>001100111111001111</row>
		<row>001100110000001100</row>
		<row>001100111111001111</row>
		<row>000000000000000000</row>
	</frame>

	<frame ms="200">
		<row>000000000000000000</row>
		<row>011001111110011111</row>
		<row>011001100000011000</row>
		<row>011001111110011111</row>
		<row>011001111110011111</row>
		<row>011001100000011000</row>
		<row>011001111110011111</row>
		<row>000000000000000000</row>
	</frame>

	<frame ms="200">
		<row>000000000000000000</row>
		<row>110011111100111110</row>
		<row>110011000000110001</row>
		<row>110011111100111110</row>
		<row>110011111100111110</row>
		<row>110011000000110001</row>
		<row>110011111100111110</row>
		<row>000000000000000000</row>
	</frame>

	<frame ms="200">
		<row>000000000000000000</row>
		<row>100111111001111100</row>
		<row>100110000001100010</row>
		<row>100111111001111100</row>
		<row>100111111001111100</row>
		<row>100110000001100010</row>
		<row>100111111001111100</row>
		<row>000000000000000000</row>
	</frame>

	<frame ms="200">
		<row>000000000000000000</row>
		<row>001111110011111000</row>
		<row>001100000011000100</row>
		<row>001111110011111000</row>
		<row>001111110011111000</row>
		<row>001100000011000100</row>
		<row>001111110011111000</row>
		<row>000000000000000000</row>
	</frame>

	<frame ms="200">
		<row>000000000000000000</row>
		<row>011111100111110001</row>
		<row>011000000110001001</row>
		<row>011111100111110001</row>
		<row>011111100111110001</row>
		<row>011000000110001001</row>
		<row>011111100111110001</row>
		<row>000000000000000000</row>
	</frame>

	<frame ms="200">
		<row>000000000000000000</row>
		<row>111111001111100011</row>
		<row>110000001100010011</row>
		<row>111111001111100011</row>
		<row>111111001111100011</row>
		<row>110000001100010011</row>
		<row>111111001111100011</row>
		<row>000000000000000000</row>
	</frame>

	<frame ms="200">
		<row>000000000000000000</row>
		<row>111110011111000111</row>
		<row>100000011000100110</row>
		<row>111110011111000111</row>
		<row>111110011111000111</row>
		<row>100000011000100110</row>
		<row>111110011111000111</row>
		<row>000000000000000000</row>
	</frame>

	<frame ms="200">
		<row>000000000000000000</row>
		<row>111100111110001111</row>
		<row>000000110001001100</row>
		<row>111100111110001111</row>
		<row>111100111110001111</row>
		<row>000000110001001100</row>
		<row>111100111110001111</row>
		<row>000000000000000000</row>
	</frame>

	<frame ms="200">
		<row>000000000000000000</row>
		<row>111001111100011111</row>
		<row>000001100010011000</row>
		<row>111001111100011111</row>
		<row>111001111100011111</row>
		<row>000001100010011000</row>
		<row>111001111100011111</row>
		<row>000000000000000000</row>
	</frame>

	<frame ms="200">
		<row>000000000000000000</row>
		<row>110011111000111111</row>
		<row>000011000100110000</row>
		<row>110011111000111111</row>
		<row>110011111000111111</row>
		<row>000011000100110000</row>
		<row>110011111000111111</row>
		<row>000000000000000000</row>
	</frame>

	<frame ms="200">
		<row>000000000000000000</row>
		<row>100111110001111110</row>
		<row>000110001001100000</row>
		<row>100111110001111110</row>
		<row>100111110001111110</row>
		<row>000110001001100000</row>
		<row>100111110001111110</row>
		<row>000000000000000000</row>
	</frame>

	<frame ms="200">
		<row>000000000000000000</row>
		<row>001111100011111100</row>
		<row>001100010011000000</row>
		<row>001111100011111100</row>
		<row>001111100011111100</row>
		<row>001100010011000000</row>
		<row>001111100011111100</row>
		<row>000000000000000000</row>
	</frame>

	<frame ms="200">
		<row>000000000000000000</row>
		<row>011111000111111001</row>
		<row>011000100110000001</row>
		<row>011111000111111001</row>
		<row>011111000111111001</row>
		<row>011000100110000001</row>
		<row>011111000111111001</row>
		<row>000000000000000000</row>
	</frame>

	<frame ms="200">
		<row>000000000000000000</row>
		<row>111110001111110011</row>
		<row>110001001100000011</row>
		<row>111110001111110011</row>
		<row>111110001111110011</row>
		<row>110001001100000011</row>
		<row>111110001111110011</row>
		<row>000000000000000000</row>
	</frame>

	<frame ms="200">
		<row>000000000000000000</row>
		<row>111100011111100110</row>
		<row>100010011000000111</row>
		<row>111100011111100110</row>
		<row>111100011111100110</row>
		<row>100010011000000110</row>
		<row>111100011111100110</row>
		<row>000000000000000000</row>
	</frame>

	<frame ms="200">
		<row>000000000000000000</row>
		<row>111000111111001100</row>
		<row>000100110000001110</row>
		<row>111000111111001101</row>
		<row>111000111111001100</row>
		<row>000100110000001100</row>
		<row>111000111111001100</row>
		<row>000000000000000000</row>
	</frame>

	<frame ms="200">
		<row>000000000000000000</row>
		<row>110001111110011000</row>
		<row>001001100000011100</row>
		<row>110001111110011010</row>
		<row>110001111110011001</row>
		<row>001001100000011000</row>
		<row>110001111110011000</row>
		<row>000000000000000000</row>
	</frame>

	<frame ms="200">
		<row>000000000000000000</row>
		<row>100011111100110000</row>
		<row>010011000000111000</row>
		<row>100011111100110100</row>
		<row>100011111100110010</row>
		<row>010011000000110001</row>
		<row>100011111100110000</row>
		<row>000000000000000000</row>
	</frame>

	<frame ms="200">
		<row>000000000000000000</row>
		<row>000111111001100001</row>
		<row>100110000001110001</row>
		<row>000111111001101001</row>
		<row>000111111001100101</row>
		<row>100110000001100011</row>
		<row>000111111001100001</row>
		<row>000000000000000000</row>
	</frame>

	<frame ms="200">
		<row>000000000000000000</row>
		<row>001111110011000011</row>
		<row>001100000011100011</row>
		<row>001111110011010011</row>
		<row>001111110011001011</row>
		<row>001100000011000111</row>
		<row>001111110011000011</row>
		<row>000000000000000000</row>
	</frame>

	<frame ms="200">
		<row>000000000000000000</row>
		<row>011111100110000110</row>
		<row>011000000111000110</row>
		<row>011111100110100110</row>
		<row>011111100110010110</row>
		<row>011000000110001110</row>
		<row>011111100110000110</row>
		<row>000000000000000000</row>
	</frame>

	<frame ms="200">
		<row>000000000000000000</row>
		<row>111111001100001100</row>
		<row>110000001110001100</row>
		<row>111111001101001100</row>
		<row>111111001100101100</row>
		<row>110000001100011100</row>
		<row>111111001100001100</row>
		<row>000000000000000000</row>
	</frame>

	<frame ms="200">
		<row>000000000000000000</row>
		<row>111110011000011000</row>
		<row>100000011100011000</row>
		<row>111110011010011000</row>
		<row>111110011001011000</row>
		<row>100000011000111000</row>
		<row>111110011000011000</row>
		<row>000000000000000000</row>
	</frame>

	<frame ms="200">
		<row>000000000000000000</row>
		<row>111100110000110000</row>
		<row>000000111000110000</row>
		<row>111100110100110000</row>
		<row>111100110010110000</row>
		<row>000000110001110000</row>
		<row>111100110000110000</row>
		<row>000000000000000000</row>
	</frame>

	<frame ms="200">
		<row>000000000000000000</row>
		<row>111001100001100001</row>
		<row>000001110001100001</row>
		<row>111001101001100001</row>
		<row>111001100101100001</row>
		<row>000001100011100000</row>
		<row>111001100001100001</row>
		<row>000000000000000000</row>
	</frame>

	<frame ms="200">
		<row>000000000000000000</row>
		<row>110011000011000011</row>
		<row>000011100011000011</row>
		<row>110011010011000011</row>
		<row>110011001011000011</row>
		<row>000011000111000000</row>
		<row>110011000011000011</row>
		<row>000000000000000000</row>
	</frame>

	<frame ms="200">
		<row>000000000000000000</row>
		<row>100110000110000110</row>
		<row>000111000110000110</row>
		<row>100110100110000110</row>
		<row>100110010110000110</row>
		<row>000110001110000000</row>
		<row>100110000110000110</row>
		<row>000000000000000000</row>
	</frame>

	<frame ms="200">
		<row>000000000000000000</row>
		<row>001100001100001100</row>
		<row>001110001100001100</row>
		<row>001101001100001100</row>
		<row>001100101100001100</row>
		<row>001100011100000000</row>
		<row>001100001100001100</row>
		<row>000000000000000000</row>
	</frame>

	<frame ms="200">
		<row>000000000000000000</row>
		<row>011000011000011000</row>
		<row>011100011000011000</row>
		<row>011010011000011000</row>
		<row>011001011000011000</row>
		<row>011000111000000000</row>
		<row>011000011000011000</row>
		<row>000000000000000000</row>
	</frame>

	<frame ms="200">
		<row>000000000000000000</row>
		<row>110000110000110000</row>
		<row>111000110000110000</row>
		<row>110100110000110000</row>
		<row>110010110000110000</row>
		<row>110001110000000000</row>
		<row>110000110000110000</row>
		<row>000000000000000000</row>
	</frame>

	<frame ms="200">
		<row>000000000000000000</row>
		<row>100001100001100000</row>
		<row>110001100001100000</row>
		<row>101001100001100000</row>
		<row>100101100001100000</row>
		<row>100011100000000000</row>
		<row>100001100001100000</row>
		<row>000000000000000000</row>
	</frame>

	<frame ms="200">
		<row>000000000000000000</row>
		<row>000011000011000001</row>
		<row>100011000011000001</row>
		<row>010011000011000001</row>
		<row>001011000011000000</row>
		<row>000111000000000000</row>
		<row>000011000011000000</row>
		<row>000000000000000000</row>
	</frame>

	<frame ms="200">
		<row>000000000000000000</row>
		<row>000110000110000010</row>
		<row>000110000110000011</row>
		<row>100110000110000011</row>
		<row>010110000110000001</row>
		<row>001110000000000000</row>
		<row>000110000110000000</row>
		<row>000000000000000000</row>
	</frame>

	<frame ms="200">
		<row>000000000000000000</row>
		<row>001100001100000100</row>
		<row>001100001100000110</row>
		<row>001100001100000110</row>
		<row>101100001100000011</row>
		<row>011100000000000001</row>
		<row>001100001100000000</row>
		<row>000000000000000000</row>
	</frame>

	<frame ms="200">
		<row>000000000000000000</row>
		<row>011000011000001000</row>
		<row>011000011000001100</row>
		<row>011000011000001100</row>
		<row>011000011000000110</row>
		<row>111000000000000011</row>
		<row>011000011000000001</row>
		<row>000000000000000000</row>
	</frame>

	<frame ms="200">
		<row>000000000000000000</row>
		<row>110000110000010000</row>
		<row>110000110000011000</row>
		<row>110000110000011000</row>
		<row>110000110000001101</row>
		<row>110000000000000111</row>
		<row>110000110000000010</row>
		<row>000000000000000000</row>
	</frame>

	<frame ms="200">
		<row>000000000000000000</row>
		<row>100001100000100000</row>
		<row>100001100000110001</row>
		<row>100001100000110001</row>
		<row>100001100000011011</row>
		<row>100000000000001110</row>
		<row>100001100000000100</row>
		<row>000000000000000000</row>
	</frame>

	<frame ms="200">
		<row>000000000000000000</row>
		<row>000011000001000001</row>
		<row>000011000001100011</row>
		<row>000011000001100011</row>
		<row>000011000000110110</row>
		<row>000000000000011100</row>
		<row>000011000000001000</row>
		<row>000000000000000000</row>
	</frame>

	<frame ms="200">
		<row>000000000000000000</row>
		<row>000110000010000010</row>
		<row>000110000011000110</row>
		<row>000110000011000110</row>
		<row>000110000001101100</row>
		<row>000000000000111000</row>
		<row>000110000000010000</row>
		<row>000000000000000000</row>
	</frame>

	<frame ms="200">
		<row>000000000000000000</row>
		<row>001100000100000100</row>
		<row>001100000110001100</row>
		<row>001100000110001100</row>
		<row>001100000011011000</row>
		<row>000000000001110000</row>
		<row>001100000000100000</row>
		<row>000000000000000000</row>
	</frame>

	<frame ms="200">
		<row>000000000000000000</row>
		<row>011000001000001001</row>
		<row>011000001100011001</row>
		<row>011000001100011001</row>
		<row>011000000110110001</row>
		<row>000000000011100001</row>
		<row>011000000001000001</row>
		<row>000000000000000000</row>
	</frame>

	<frame ms="200">
		<row>000000000000000000</row>
		<row>110000010000010011</row>
		<row>110000011000110011</row>
		<row>110000011000110011</row>
		<row>110000001101100011</row>
		<row>000000000111000011</row>
		<row>110000000010000011</row>
		<row>000000000000000000</row>
	</frame>

	<frame ms="200">
		<row>000000000000000000</row>
		<row>100000100000100110</row>
		<row>100000110001100110</row>
		<row>100000110001100110</row>
		<row>100000011011000110</row>
		<row>000000001110000110</row>
		<row>100000000100000110</row>
		<row>000000000000000000</row>
	</frame>

	<frame ms="200">
		<row>000000000000000000</row>
		<row>000001000001001100</row>
		<row>000001100011001100</row>
		<row>000001100011001100</row>
		<row>000000110110001100</row>
		<row>000000011100001100</row>
		<row>000000001000001100</row>
		<row>000000000000000000</row>
	</frame>

	<frame ms="200">
		<row>000000000000000000</row>
		<row>000010000010011001</row>
		<row>000011000110011001</row>
		<row>000011000110011001</row>
		<row>000001101100011001</row>
		<row>000000111000011001</row>
		<row>000000010000011001</row>
		<row>000000000000000000</row>
	</frame>

	<frame ms="200">
		<row>000000000000000000</row>
		<row>000100000100110011</row>
		<row>000110001100110011</row>
		<row>000110001100110011</row>
		<row>000011011000110011</row>
		<row>000001110000110011</row>
		<row>000000100000110011</row>
		<row>000000000000000000</row>
	</frame>

	<frame ms="200">
		<row>000000000000000000</row>
		<row>001000001001100111</row>
		<row>001100011001100110</row>
		<row>001100011001100111</row>
		<row>000110110001100111</row>
		<row>000011100001100110</row>
		<row>000001000001100111</row>
		<row>000000000000000000</row>
	</frame>

	<frame ms="200">
		<row>000000000000000000</row>
		<row>010000010011001111</row>
		<row>011000110011001100</row>
		<row>011000110011001111</row>
		<row>001101100011001111</row>
		<row>000111000011001100</row>
		<row>000010000011001111</row>
		<row>000000000000000000</row>
	</frame>

	<frame ms="200">
		<row>000000000000000000</row>
		<row>100000100110011111</row>
		<row>110001100110011000</row>
		<row>110001100110011111</row>
		<row>011011000110011111</row>
		<row>001110000110011000</row>
		<row>000100000110011111</row>
		<row>000000000000000000</row>
	</frame>

	<frame ms="200">
		<row>000000000000000000</row>
		<row>000001001100111111</row>
		<row>100011001100110000</row>
		<row>100011001100111111</row>
		<row>110110001100111111</row>
		<row>011100001100110000</row>
		<row>001000001100111111</row>
		<row>000000000000000000</row>
	</frame>

	<frame ms="200">
		<row>000000000000000000</row>
		<row>000010011001111110</row>
		<row>000110011001100000</row>
		<row>000110011001111110</row>
		<row>101100011001111110</row>
		<row>111000011001100000</row>
		<row>010000011001111110</row>
		<row>000000000000000000</row>
	</frame>

	<frame ms="200">
		<row>000000000000000000</row>
		<row>000100110011111100</row>
		<row>001100110011000000</row>
		<row>001100110011111100</row>
		<row>011000110011111100</row>
		<row>110000110011000000</row>
		<row>100000110011111100</row>
		<row>000000000000000000</row>
	</frame>

	<frame ms="200">
		<row>000000000000000000</row>
		<row>001001100111111001</row>
		<row>011001100110000001</row>
		<row>011001100111111001</row>
		<row>110001100111111001</row>
		<row>100001100110000001</row>
		<row>000001100111111001</row>
		<row>000000000000000000</row>
	</frame>

	<frame ms="200">
		<row>000000000000000000</row>
		<row>010011001111110011</row>
		<row>110011001100000011</row>
		<row>110011001111110011</row>
		<row>100011001111110011</row>
		<row>000011001100000011</row>
		<row>000011001111110011</row>
		<row>000000000000000000</row>
	</frame>

	<frame ms="200">
		<row>000000000000000000</row>
		<row>100110011111100110</row>
		<row>100110011000000110</row>
		<row>100110011111100110</row>
		<row>000110011111100110</row>
		<row>000110011000000111</row>
		<row>000110011111100111</row>
		<row>000000000000000000</row>
	</frame>

	<frame ms="200">
		<row>000000000000000000</row>
		<row>001100111111001100</row>
		<row>001100110000001100</row>
		<row>001100111111001100</row>
		<row>001100111111001100</row>
		<row>001100110000001111</row>
		<row>001100111111001111</row>
		<row>000000000000000000</row>
	</frame>

	<frame ms="200">
		<row>000000000000000000</row>
		<row>011001111110011000</row>
		<row>011001100000011000</row>
		<row>011001111110011000</row>
		<row>011001111110011000</row>
		<row>011001100000011111</row>
		<row>011001111110011111</row>
		<row>000000000000000000</row>
	</frame>

	<frame ms="200">
		<row>000000000000000000</row>
		<row>110011111100110000</row>
		<row>110011000000110000</row>
		<row>110011111100110000</row>
		<row>110011111100110000</row>
		<row>110011000000111111</row>
		<row>110011111100111111</row>
		<row>000000000000000000</row>
	</frame>

	<frame ms="200">
		<row>000000000000000000</row>
		<row>100111111001100000</row>
		<row>100110000001100000</row>
		<row>100111111001100000</row>
		<row>100111111001100000</row>
		<row>100110000001111110</row>
		<row>100111111001111110</row>
		<row>000000000000000000</row>
	</frame>

	<frame ms="200">
		<row>000000000000000000</row>
		<row>001111110011000000</row>
		<row>001100000011000000</row>
		<row>001111110011000000</row>
		<row>001111110011000000</row>
		<row>001100000011111100</row>
		<row>001111110011111100</row>
		<row>000000000000000000</row>
	</frame>

	<frame ms="200">
		<row>000000000000000000</row>
		<row>011111100110000000</row>
		<row>011000000110000000</row>
		<row>011111100110000000</row>
		<row>011111100110000000</row>
		<row>011000000111111000</row>
		<row>011111100111111000</row>
		<row>000000000000000000</row>
	</frame>

	<frame ms="200">
		<row>000000000000000000</row>
		<row>111111001100000000</row>
		<row>110000001100000000</row>
		<row>111111001100000000</row>
		<row>111111001100000000</row>
		<row>110000001111110000</row>
		<row>111111001111110000</row>
		<row>000000000000000000</row>
	</frame>

	<frame ms="200">
		<row>000000000000000000</row>
		<row>111110011000000000</row>
		<row>100000011000000000</row>
		<row>111110011000000000</row>
		<row>111110011000000000</row>
		<row>100000011111100000</row>
		<row>111110011111100000</row>
		<row>000000000000000000</row>
	</frame>

	<frame ms="200">
		<row>000000000000000000</row>
		<row>111100110000000000</row>
		<row>000000110000000001</row>
		<row>111100110000000001</row>
		<row>111100110000000001</row>
		<row>000000111111000001</row>
		<row>111100111111000000</row>
		<row>000000000000000000</row>
	</frame>

	<frame ms="200">
		<row>000000000000000000</row>
		<row>111001100000000000</row>
		<row>000001100000000011</row>
		<row>111001100000000011</row>
		<row>111001100000000011</row>
		<row>000001111110000011</row>
		<row>111001111110000000</row>
		<row>000000000000000000</row>
	</frame>

	<frame ms="200">
		<row>000000000000000000</row>
		<row>110011000000000001</row>
		<row>000011000000000110</row>
		<row>110011000000000110</row>
		<row>110011000000000110</row>
		<row>000011111100000110</row>
		<row>110011111100000001</row>
		<row>000000000000000000</row>
	</frame>

	<frame ms="200">
		<row>000000000000000000</row>
		<row>100110000000000011</row>
		<row>000110000000001100</row>
		<row>100110000000001100</row>
		<row>100110000000001101</row>
		<row>000111111000001100</row>
		<row>100111111000000011</row>
		<row>000000000000000000</row>
	</frame>

	<frame ms="200">
		<row>000000000000000000</row>
		<row>001100000000000111</row>
		<row>001100000000011000</row>
		<row>001100000000011000</row>
		<row>001100000000011011</row>
		<row>001111110000011000</row>
		<row>001111110000000111</row>
		<row>000000000000000000</row>
	</frame>

	<frame ms="200">
		<row>000000000000000000</row>
		<row>011000000000001110</row>
		<row>011000000000110000</row>
		<row>011000000000110000</row>
		<row>011000000000110111</row>
		<row>011111100000110001</row>
		<row>011111100000001110</row>
		<row>000000000000000000</row>
	</frame>

	<frame ms="200">
		<row>000000000000000000</row>
		<row>110000000000011100</row>
		<row>110000000001100000</row>
		<row>110000000001100000</row>
		<row>110000000001101110</row>
		<row>111111000001100010</row>
		<row>111111000000011100</row>
		<row>000000000000000000</row>
	</frame>

	<frame ms="200">
		<row>000000000000000000</row>
		<row>100000000000111000</row>
		<row>100000000011000000</row>
		<row>100000000011000000</row>
		<row>100000000011011100</row>
		<row>111110000011000100</row>
		<row>111110000000111000</row>
		<row>000000000000000000</row>
	</frame>

	<frame ms="200">
		<row>000000000000000000</row>
		<row>000000000001110001</row>
		<row>000000000110000001</row>
		<row>000000000110000001</row>
		<row>000000000110111001</row>
		<row>111100000110001001</row>
		<row>111100000001110001</row>
		<row>000000000000000000</row>
	</frame>

	<frame ms="200">
		<row>000000000000000000</row>
		<row>000000000011100011</row>
		<row>000000001100000011</row>
		<row>000000001100000011</row>
		<row>000000001101110011</row>
		<row>111000001100010011</row>
		<row>111000000011100011</row>
		<row>000000000000000000</row>
	</frame>

	<frame ms="200">
		<row>000000000000000000</row>
		<row>000000000111000110</row>
		<row>000000011000000110</row>
		<row>000000011000000110</row>
		<row>000000011011100110</row>
		<row>110000011000100111</row>
		<row>110000000111000111</row>
		<row>000000000000000000</row>
	</frame>

	<frame ms="200">
		<row>000000000000000000</row>
		<row>000000001110001100</row>
		<row>000000110000001100</row>
		<row>000000110000001100</row>
		<row>000000110111001100</row>
		<row>100000110001001111</row>
		<row>100000001110001111</row>
		<row>000000000000000000</row>
	</frame>

	<frame ms="200">
		<row>000000000000000000</row>
		<row>000000011100011000</row>
		<row>000001100000011000</row>
		<row>000001100000011000</row>
		<row>000001101110011000</row>
		<row>000001100010011111</row>
		<row>000000011100011111</row>
		<row>000000000000000000</row>
	</frame>

	<frame ms="200">
		<row>000000000000000000</row>
		<row>000000111000110000</row>
		<row>000011000000110000</row>
		<row>000011000000110000</row>
		<row>000011011100110000</row>
		<row>000011000100111111</row>
		<row>000000111000111111</row>
		<row>000000000000000000</row>
	</frame>

	<frame ms="200">
		<row>000000000000000000</row>
		<row>000001110001100000</row>
		<row>000110000001100000</row>
		<row>000110000001100000</row>
		<row>000110111001100000</row>
		<row>000110001001111110</row>
		<row>000001110001111110</row>
		<row>000000000000000000</row>
	</frame>

	<frame ms="200">
		<row>000000000000000000</row>
		<row>000011100011000000</row>
		<row>001100000011000000</row>
		<row>001100000011000000</row>
		<row>001101110011000000</row>
		<row>001100010011111100</row>
		<row>000011100011111100</row>
		<row>000000000000000000</row>
	</frame>

	<frame ms="200">
		<row>000000000000000000</row>
		<row>000111000110000001</row>
		<row>011000000110000000</row>
		<row>011000000110000001</row>
		<row>011011100110000001</row>
		<row>011000100111111001</row>
		<row>000111000111111000</row>
		<row>000000000000000000</row>
	</frame>

	<frame ms="200">
		<row>000000000000000000</row>
		<row>001110001100000011</row>
		<row>110000001100000000</row>
		<row>110000001100000011</row>
		<row>110111001100000011</row>
		<row>110001001111110011</row>
		<row>001110001111110001</row>
		<row>000000000000000000</row>
	</frame>

	<frame ms="200">
		<row>000000000000000000</row>
		<row>011100011000000110</row>
		<row>100000011000000000</row>
		<row>100000011000000110</row>
		<row>101110011000000110</row>
		<row>100010011111100111</row>
		<row>011100011111100011</row>
		<row>000000000000000000</row>
	</frame>

	<frame ms="200">
		<row>000000000000000000</row>
		<row>111000110000001100</row>
		<row>000000110000000000</row>
		<row>000000110000001100</row>
		<row>011100110000001100</row>
		<row>000100111111001111</row>
		<row>111000111111000111</row>
		<row>000000000000000000</row>
	</frame>

	<frame ms="200">
		<row>000000000000000000</row>
		<row>110001100000011001</row>
		<row>000001100000000000</row>
		<row>000001100000011001</row>
		<row>111001100000011001</row>
		<row>001001111110011111</row>
		<row>110001111110001111</row>
		<row>000000000000000000</row>
	</frame>

	<frame ms="200">
		<row>000000000000000000</row>
		<row>100011000000110011</row>
		<row>000011000000000000</row>
		<row>000011000000110011</row>
		<row>110011000000110011</row>
		<row>010011111100111111</row>
		<row>100011111100011110</row>
		<row>000000000000000000</row>
	</frame>

	<frame ms="200">
		<row>000000000000000000</row>
		<row>000110000001100110</row>
		<row>000110000000000000</row>
		<row>000110000001100110</row>
		<row>100110000001100110</row>
		<row>100111111001111110</row>
		<row>000111111000111100</row>
		<row>000000000000000000</row>
	</frame>

	<frame ms="200">
		<row>000000000000000000</row>
		<row>001100000011001100</row>
		<row>001100000000000000</row>
		<row>001100000011001100</row>
		<row>001100000011001100</row>
		<row>001111110011111100</row>
		<row>001111110001111000</row>
		<row>000000000000000000</row>
	</frame>

	<frame ms="200">
		<row>000000000000000000</row>
		<row>011000000110011000</row>
		<row>011000000000000000</row>
		<row>011000000110011000</row>
		<row>011000000110011000</row>
		<row>011111100111111000</row>
		<row>011111100011110000</row>
		<row>000000000000000000</row>
	</frame>

	<frame ms="200">
		<row>000000000000000000</row>
		<row>110000001100110000</row>
		<row>110000000000000000</row>
		<row>110000001100110001</row>
		<row>110000001100110001</row>
		<row>111111001111110000</row>
		<row>111111000111100000</row>
		<row>000000000000000000</row>
	</frame>

	<frame ms="200">
		<row>000000000000000000</row>
		<row>100000011001100000</row>
		<row>100000000000000001</row>
		<row>100000011001100011</row>
		<row>100000011001100011</row>
		<row>111110011111100001</row>
		<row>111110001111000000</row>
		<row>000000000000000000</row>
	</frame>

	<frame ms="200">
		<row>000000000000000000</row>
		<row>000000110011000001</row>
		<row>000000000000000011</row>
		<row>000000110011000110</row>
		<row>000000110011000110</row>
		<row>111100111111000011</row>
		<row>111100011110000001</row>
		<row>000000000000000000</row>
	</frame>

	<frame ms="200">
		<row>000000000000000000</row>
		<row>000001100110000011</row>
		<row>000000000000000110</row>
		<row>000001100110001100</row>
		<row>000001100110001100</row>
		<row>111001111110000110</row>
		<row>111000111100000011</row>
		<row>000000000000000000</row>
	</frame>

	<frame ms="200">
		<row>000000000000000000</row>
		<row>000011001100000111</row>
		<row>000000000000001100</row>
		<row>000011001100011000</row>
		<row>000011001100011000</row>
		<row>110011111100001100</row>
		<row>110001111000000111</row>
		<row>000000000000000000</row>
	</frame>

	<frame ms="200">
		<row>000000000000000000</row>
		<row>000110011000001110</row>
		<row>000000000000011000</row>
		<row>000110011000110000</row>
		<row>000110011000110000</row>
		<row>100111111000011000</row>
		<row>100011110000001110</row>
		<row>000000000000000000</row>
	</frame>

	<frame ms="200">
		<row>000000000000000000</row>
		<row>001100110000011100</row>
		<row>000000000000110000</row>
		<row>001100110001100000</row>
		<row>001100110001100000</row>
		<row>001111110000110000</row>
		<row>000111100000011100</row>
		<row>000000000000000000</row>
	</frame>

	<frame ms="200">
		<row>000000000000000000</row>
		<row>011001100000111001</row>
		<row>000000000001100001</row>
		<row>011001100011000001</row>
		<row>011001100011000001</row>
		<row>011111100001100001</row>
		<row>001111000000111001</row>
		<row>000000000000000000</row>
	</frame>

	<frame ms="200">
		<row>000000000000000000</row>
		<row>110011000001110011</row>
		<row>000000000011000011</row>
		<row>110011000110000011</row>
		<row>110011000110000011</row>
		<row>111111000011000011</row>
		<row>011110000001110011</row>
		<row>000000000000000000</row>
	</frame>

	<frame ms="200">
		<row>000000000000000000</row>
		<row>100110000011100110</row>
		<row>000000000110000110</row>
		<row>100110001100000111</row>
		<row>100110001100000111</row>
		<row>111110000110000110</row>
		<row>111100000011100110</row>
		<row>000000000000000000</row>
	</frame>

	<frame ms="200">
		<row>000000000000000000</row>
		<row>001100000111001100</row>
		<row>000000001100001101</row>
		<row>001100011000001110</row>
		<row>001100011000001110</row>
		<row>111100001100001101</row>
		<row>111000000111001100</row>
		<row>000000000000000000</row>
	</frame>

	<frame ms="200">
		<row>000000000000000000</row>
		<row>011000001110011001</row>
		<row>000000011000011010</row>
		<row>011000110000011100</row>
		<row>011000110000011100</row>
		<row>111000011000011010</row>
		<row>110000001110011001</row>
		<row>000000000000000000</row>
	</frame>

	<frame ms="200">
		<row>000000000000000000</row>
		<row>110000011100110010</row>
		<row>000000110000110100</row>
		<row>110001100000111000</row>
		<row>110001100000111000</row>
		<row>110000110000110100</row>
		<row>100000011100110010</row>
		<row>000000000000000000</row>
	</frame>

	<frame ms="200">
		<row>000000000000000000</row>
		<row>100000111001100100</row>
		<row>000001100001101000</row>
		<row>100011000001110000</row>
		<row>100011000001110000</row>
		<row>100001100001101000</row>
		<row>000000111001100100</row>
		<row>000000000000000000</row>
	</frame>

	<frame ms="200">
		<row>000000000000000000</row>
		<row>000001110011001000</row>
		<row>000011000011010000</row>
		<row>000110000011100000</row>
		<row>000110000011100000</row>
		<row>000011000011010000</row>
		<row>000001110011001000</row>
		<row>000000000000000000</row>
	</frame>

	<frame ms="200">
		<row>000000000000000000</row>
		<row>000011100110010000</row>
		<row>000110000110100000</row>
		<row>001100000111000000</row>
		<row>001100000111000000</row>
		<row>000110000110100000</row>
		<row>000011100110010000</row>
		<row>000000000000000000</row>
	</frame>

	<frame ms="200">
		<row>000000000000000000</row>
		<row>000111001100100000</row>
		<row>001100001101000000</row>
		<row>011000001110000000</row>
		<row>011000001110000000</row>
		<row>001100001101000000</row>
		<row>000111001100100000</row>
		<row>000000000000000000</row>
	</frame>

	<frame ms="200">
		<row>000000000000000000</row>
		<row>001110011001000001</row>
		<row>011000011010000000</row>
		<row>110000011100000000</row>
		<row>110000011100000000</row>
		<row>011000011010000001</row>
		<row>001110011001000001</row>
		<row>000000000000000000</row>
	</frame>

	<frame ms="200">
		<row>000000000000000000</row>
		<row>011100110010000011</row>
		<row>110000110100000000</row>
		<row>100000111000000000</row>
		<row>100000111000000001</row>
		<row>110000110100000011</row>
		<row>011100110010000011</row>
		<row>000000000000000000</row>
	</frame>

	<frame ms="200">
		<row>000000000000000000</row>
		<row>111001100100000111</row>
		<row>100001101000000000</row>
		<row>000001110000000000</row>
		<row>000001110000000011</row>
		<row>100001101000000110</row>
		<row>111001100100000111</row>
		<row>000000000000000000</row>
	</frame>

	<frame ms="200">
		<row>000000000000000000</row>
		<row>110011001000001111</row>
		<row>000011010000000000</row>
		<row>000011100000000000</row>
		<row>000011100000000111</row>
		<row>000011010000001100</row>
		<row>110011001000001111</row>
		<row>000000000000000000</row>
	</frame>

	<frame ms="200">
		<row>000000000000000000</row>
		<row>100110010000011111</row>
		<row>000110100000000001</row>
		<row>000111000000000001</row>
		<row>000111000000001110</row>
		<row>000110100000011000</row>
		<row>100110010000011111</row>
		<row>000000000000000000</row>
	</frame>

	<frame ms="200">
		<row>000000000000000000</row>
		<row>001100100000111110</row>
		<row>001101000000000011</row>
		<row>001110000000000011</row>
		<row>001110000000011100</row>
		<row>001101000000110000</row>
		<row>001100100000111111</row>
		<row>000000000000000000</row>
	</frame>

	<frame ms="200">
		<row>000000000000000000</row>
		<row>011001000001111100</row>
		<row>011010000000000110</row>
		<row>011100000000000110</row>
		<row>011100000000111000</row>
		<row>011010000001100000</row>
		<row>011001000001111110</row>
		<row>000000000000000000</row>
	</frame>

	<frame ms="200">
		<row>000000000000000000</row>
		<row>110010000011111000</row>
		<row>110100000000001100</row>
		<row>111000000000001100</row>
		<row>111000000001110000</row>
		<row>110100000011000000</row>
		<row>110010000011111100</row>
		<row>000000000000000000</row>
	</frame>

	<frame ms="200">
		<row>000000000000000000</row>
		<row>100100000111110000</row>
		<row>101000000000011000</row>
		<row>110000000000011001</row>
		<row>110000000011100001</row>
		<row>101000000110000000</row>
		<row>100100000111111000</row>
		<row>000000000000000000</row>
	</frame>

	<frame ms="200">
		<row>000000000000000000</row>
		<row>001000001111100000</row>
		<row>010000000000110001</row>
		<row>100000000000110011</row>
		<row>100000000111000011</row>
		<row>010000001100000001</row>
		<row>001000001111110000</row>
		<row>000000000000000000</row>
	</frame>

	<frame ms="200">
		<row>000000000000000000</row>
		<row>010000011111000001</row>
		<row>100000000001100011</row>
		<row>000000000001100110</row>
		<row>000000001110000110</row>
		<row>100000011000000011</row>
		<row>010000011111100001</row>
		<row>000000000000000000</row>
	</frame>

	<frame ms="200">
		<row>000000000000000000</row>
		<row>100000111110000011</row>
		<row>000000000011000111</row>
		<row>000000000011001100</row>
		<row>000000011100001100</row>
		<row>000000110000000111</row>
		<row>100000111111000011</row>
		<row>000000000000000000</row>
	</frame>

	<frame ms="200">
		<row>000000000000000000</row>
		<row>000001111100000110</row>
		<row>000000000110001111</row>
		<row>000000000110011001</row>
		<row>000000111000011001</row>
		<row>000001100000001111</row>
		<row>000001111110000110</row>
		<row>000000000000000000</row>
	</frame>

	<frame ms="200">
		<row>000000000000000000</row>
		<row>000011111000001100</row>
		<row>000000001100011110</row>
		<row>000000001100110011</row>
		<row>000001110000110011</row>
		<row>000011000000011110</row>
		<row>000011111100001100</row>
		<row>000000000000000000</row>
	</frame>

	<frame ms="200">
		<row>000000000000000000</row>
		<row>000111110000011000</row>
		<row>000000011000111100</row>
		<row>000000011001100110</row>
		<row>000011100001100110</row>
		<row>000110000000111100</row>
		<row>000111111000011000</row>
		<row>000000000000000000</row>
	</frame>

	<frame ms="200">
		<row>000000000000000000</row>
		<row>001111100000110000</row>
		<row>000000110001111000</row>
		<row>000000110011001100</row>
		<row>000111000011001100</row>
		<row>001100000001111000</row>
		<row>001111110000110000</row>
		<row>000000000000000000</row>
	</frame>

	<frame ms="200">
		<row>000000000000000000</row>
		<row>011111000001100000</row>
		<row>000001100011110000</row>
		<row>000001100110011001</row>
		<row>001110000110011001</row>
		<row>011000000011110000</row>
		<row>011111100001100000</row>
		<row>000000000000000000</row>
	</frame>

	<frame ms="200">
		<row>000000000000000000</row>
		<row>111110000011000000</row>
		<row>000011000111100001</row>
		<row>000011001100110011</row>
		<row>011100001100110011</row>
		<row>110000000111100001</row>
		<row>111111000011000000</row>
		<row>000000000000000000</row>
	</frame>

	<frame ms="200">
		<row>000000000000000000</row>
		<row>111100000110000001</row>
		<row>000110001111000011</row>
		<row>000110011001100110</row>
		<row>111000011001100110</row>
		<row>100000001111000011</row>
		<row>111110000110000001</row>
		<row>000000000000000000</row>
	</frame>

	<frame ms="200">
		<row>000000000000000000</row>
		<row>111000001100000011</row>
		<row>001100011110000111</row>
		<row>001100110011001100</row>
		<row>110000110011001100</row>
		<row>000000011110000111</row>
		<row>111100001100000011</row>
		<row>000000000000000000</row>
	</frame>

	<frame ms="200">
		<row>000000000000000000</row>
		<row>110000011000000110</row>
		<row>011000111100001111</row>
		<row>011001100110011001</row>
		<row>100001100110011001</row>
		<row>000000111100001111</row>
		<row>111000011000000110</row>
		<row>000000000000000000</row>
	</frame>

	<frame ms="200">
		<row>000000000000000000</row>
		<row>100000110000001100</row>
		<row>110001111000011110</row>
		<row>110011001100110011</row>
		<row>000011001100110011</row>
		<row>000001111000011110</row>
		<row>110000110000001100</row>
		<row>000000000000000000</row>
	</frame>

	<frame ms="200">
		<row>000000000000000000</row>
		<row>000001100000011000</row>
		<row>100011110000111100</row>
		<row>100110011001100110</row>
		<row>000110011001100110</row>
		<row>000011110000111100</row>
		<row>100001100000011000</row>
		<row>000000000000000000</row>
	</frame>

	<frame ms="200">
		<row>000000000000000000</row>
		<row>000011000000110000</row>
		<row>000111100001111000</row>
		<row>001100110011001100</row>
		<row>001100110011001100</row>
		<row>000111100001111000</row>
		<row>000011000000110000</row>
		<row>000000000000000000</row>
	</frame>

	<frame ms="200">
		<row>000000000000000000</row>
		<row>000110000001100001</row>
		<row>001111000011110000</row>
		<row>011001100110011000</row>
		<row>011001100110011000</row>
		<row>001111000011110001</row>
		<row>000110000001100001</row>
		<row>000000000000000000</row>
	</frame>

	<frame ms="200">
		<row>000000000000000000</row>
		<row>001100000011000011</row>
		<row>011110000111100000</row>
		<row>110011001100110000</row>
		<row>110011001100110001</row>
		<row>011110000111100011</row>
		<row>001100000011000011</row>
		<row>000000000000000000</row>
	</frame>

	<frame ms="200">
		<row>000000000000000000</row>
		<row>011000000110000111</row>
		<row>111100001111000000</row>
		<row>100110011001100000</row>
		<row>100110011001100011</row>
		<row>111100001111000110</row>
		<row>011000000110000111</row>
		<row>000000000000000000</row>
	</frame>

	<frame ms="200">
		<row>000000000000000000</row>
		<row>110000001100001111</row>
		<row>111000011110000000</row>
		<row>001100110011000000</row>
		<row>001100110011000111</row>
		<row>111000011110001100</row>
		<row>110000001100001111</row>
		<row>000000000000000000</row>
	</frame>

	<frame ms="200">
		<row>000000000000000000</row>
		<row>100000011000011111</row>
		<row>110000111100000001</row>
		<row>011001100110000001</row>
		<row>011001100110001110</row>
		<row>110000111100011000</row>
		<row>100000011000011111</row>
		<row>000000000000000000</row>
	</frame>

	<frame ms="200">
		<row>000000000000000000</row>
		<row>000000110000111110</row>
		<row>100001111000000011</row>
		<row>110011001100000011</row>
		<row>110011001100011100</row>
		<row>100001111000110000</row>
		<row>000000110000111111</row>
		<row>000000000000000000</row>
	</frame>

	<frame ms="200">
		<row>000000000000000000</row>
		<row>000001100001111100</row>
		<row>000011110000000110</row>
		<row>100110011000000110</row>
		<row>100110011000111000</row>
		<row>000011110001100000</row>
		<row>000001100001111110</row>
		<row>000000000000000000</row>
	</frame>

	<frame ms="200">
		<row>000000000000000000</row>
		<row>000011000011111000</row>
		<row>000111100000001100</row>
		<row>001100110000001100</row>
		<row>001100110001110000</row>
		<row>000111100011000000</row>
		<row>000011000011111100</row>
		<row>000000000000000000</row>
	</frame>

	<frame ms="200">
		<row>000000000000000000</row>
		<row>000110000111110000</row>
		<row>001111000000011000</row>
		<row>011001100000011000</row>
		<row>011001100011100000</row>
		<row>001111000110000000</row>
		<row>000110000111111000</row>
		<row>000000000000000000</row>
	</frame>

	<frame ms="200">
		<row>000000000000000000</row>
		<row>001100001111100000</row>
		<row>011110000000110000</row>
		<row>110011000000110000</row>
		<row>110011000111000000</row>
		<row>011110001100000000</row>
		<row>001100001111110000</row>
		<row>000000000000000000</row>
	</frame>

	<frame ms="200">
		<row>000000000000000000</row>
		<row>011000011111000001</row>
		<row>111100000001100001</row>
		<row>100110000001100001</row>
		<row>100110001110000001</row>
		<row>111100011000000000</row>
		<row>011000011111100001</row>
		<row>000000000000000000</row>
	</frame>

	<frame ms="200">
		<row>000000000000000000</row>
		<row>110000111110000011</row>
		<row>111000000011000011</row>
		<row>001100000011000011</row>
		<row>001100011100000011</row>
		<row>111000110000000000</row>
		<row>110000111111000011</row>
		<row>000000000000000000</row>
	</frame>

	<frame ms="200">
		<row>000000000000000000</row>
		<row>100001111100000110</row>
		<row>110000000110000110</row>
		<row>011000000110000110</row>
		<row>011000111000000110</row>
		<row>110001100000000000</row>
		<row>100001111110000110</row>
		<row>000000000000000000</row>
	</frame>

	<frame ms="200">
		<row>000000000000000000</row>
		<row>000011111000001100</row>
		<row>100000001100001100</row>
		<row>110000001100001100</row>
		<row>110001110000001100</row>
		<row>100011000000000000</row>
		<row>000011111100001100</row>
		<row>000000000000000000</row>
	</frame>

	<frame ms="200">
		<row>000000000000000000</row>
		<row>000111110000011000</row>
		<row>000000011000011000</row>
		<row>100000011000011000</row>
		<row>100011100000011000</row>
		<row>000110000000000000</row>
		<row>000111111000011000</row>
		<row>000000000000000000</row>
	</frame>

	<frame ms="200">
		<row>000000000000000000</row>
		<row>001111100000110000</row>
		<row>000000110000110000</row>
		<row>000000110000110000</row>
		<row>000111000000110000</row>
		<row>001100000000000000</row>
		<row>001111110000110000</row>
		<row>000000000000000000</row>
	</frame>

	<frame ms="200">
		<row>000000000000000000</row>
		<row>011111000001100000</row>
		<row>000001100001100000</row>
		<row>000001100001100000</row>
		<row>001110000001100000</row>
		<row>011000000000000000</row>
		<row>011111100001100000</row>
		<row>000000000000000000</row>
	</frame>

	<frame ms="200">
		<row>000000000000000000</row>
		<row>111110000011000000</row>
		<row>000011000011000000</row>
		<row>000011000011000000</row>
		<row>011100000011000000</row>
		<row>110000000000000000</row>
		<row>111111000011000000</row>
		<row>000000000000000000</row>
	</frame>

	<frame ms="200">
		<row>000000000000000000</row>
		<row>111100000110000000</row>
		<row>000110000110000000</row>
		<row>000110000110000000</row>
		<row>111000000110000000</row>
		<row>100000000000000000</row>
		<row>111110000110000000</row>
		<row>000000000000000000</row>
	</frame>

	<frame ms="200">
		<row>000000000000000000</row>
		<row>111000001100000000</row>
		<row>001100001100000000</row>
		<row>001100001100000000</row>
		<row>110000001100000000</row>
		<row>000000000000000000</row>
		<row>111100001100000000</row>
		<row>000000000000000000</row>
	</frame>

	<frame ms="200">
		<row>000000000000000000</row>
		<row>110000011000000000</row>
		<row>011000011000000000</row>
		<row>011000011000000000</row>
		<row>100000011000000000</row>
		<row>000000000000000000</row>
		<row>111000011000000000</row>
		<row>000000000000000000</row>
	</frame>

	<frame ms="200">
		<row>000000000000000000</row>
		<row>100000110000000000</row>
		<row>110000110000000000</row>
		<row>110000110000000000</row>
		<row>000000110000000000</row>
		<row>000000000000000000</row>
		<row>110000110000000000</row>
		<row>000000000000000000</row>
	</frame>

	<frame ms="200">
		<row>000000000000000000</row>
		<row>000001100000000000</row>
		<row>100001100000000000</row>
		<row>100001100000000000</row>
		<row>000001100000000000</row>
		<row>000000000000000000</row>
		<row>100001100000000000</row>
		<row>000000000000000000</row>
	</frame>

	<frame ms="200">
		<row>000000000000000000</row>
		<row>000011000000000000</row>
		<row>000011000000000000</row>
		<row>000011000000000000</row>
		<row>000011000000000000</row>
		<row>000000000000000000</row>
		<row>000011000000000000</row>
		<row>000000000000000000</row>
	</frame>

	<frame ms="200">
		<row>000000000000000000</row>
		<row>000110000000000000</row>
		<row>000110000000000000</row>
		<row>000110000000000000</row>
		<row>000110000000000000</row>
		<row>000000000000000000</row>
		<row>000110000000000000</row>
		<row>000000000000000000</row>
	</frame>

	<frame ms="200">
		<row>000000000000000000</row>
		<row>001100000000000000</row>
		<row>001100000000000000</row>
		<row>001100000000000000</row>
		<row>001100000000000000</row>
		<row>000000000000000000</row>
		<row>001100000000000000</row>
		<row>000000000000000000</row>
	</frame>

	<frame ms="200">
		<row>000000000000000000</row>
		<row>011000000000000000</row>
		<row>011000000000000000</row>
		<row>011000000000000000</row>
		<row>011000000000000000</row>
		<row>000000000000000000</row>
		<row>011000000000000000</row>
		<row>000000000000000000</row>
	</frame>

	<frame ms="200">
		<row>000000000000000000</row>
		<row>110000000000000000</row>
		<row>110000000000000000</row>
		<row>110000000000000000</row>
		<row>110000000000000000</row>
		<row>000000000000000000</row>
		<row>110000000000000000</row>
		<row>000000000000000000</row>
	</frame>

	<frame ms="200">
		<row>000000000000000000</row>
		<row>100000000000000000</row>
		<row>100000000000000000</row>
		<row>100000000000000000</row>
		<row>100000000000000000</row>
		<row>000000000000000000</row>
		<row>100000000000000000</row>
		<row>000000000000000000</row>
	</frame>

	<frame ms="200">
		<row>000000000000000000</row>
		<row>000000000000000000</row>
		<row>000000000000000000</row>
		<row>000000000000000000</row>
		<row>000000000000000000</row>
		<row>000000000000000000</row>
		<row>000000000000000000</row>
		<row>000000000000000000</row>
	</frame>

	<frame ms="2500">
		<row>111101111101000100</row>
		<row>100001000101101100</row>
		<row>111001111101010100</row>
		<row>100001000101000100</row>
		<row>100001000101000101</row>
		<row>000000000000000000</row>
		<row>000000000000000000</row>
		<row>000000000000000000</row>
	</frame>

	<frame ms="200">
		<row>000000000000000000</row>
		<row>000000000000000000</row>
		<row>000000000000000000</row>
		<row>000000000000000000</row>
		<row>000000000000000000</row>
		<row>000000000000000000</row>
		<row>000000000000000000</row>
		<row>000000000000000000</row>
	</frame>

	<frame ms="200">
		<row>000000000000000000</row>
		<row>000000000000000000</row>
		<row>000000000000000000</row>
		<row>000000000000000000</row>
		<row>000000000000000000</row>
		<row>000000000000000000</row>
		<row>000000000000000000</row>
		<row>000000000000000000</row>
	</frame>

	<frame ms="200">
		<row>000000000000000000</row>
		<row>000000000000000000</row>
		<row>000000000000000000</row>
		<row>000000000000000000</row>
		<row>000000000000000000</row>
		<row>000000000000000000</row>
		<row>000000000000000000</row>
		<row>000000000000000000</row>
	</frame>

	<frame ms="5000">
		<row>000111100001111000</row>
		<row>000100100001001000</row>
		<row>000111110011111000</row>
		<row>000000001100000000</row>
		<row>000000110011000000</row>
		<row>000001100001100000</row>
		<row>000011000000110000</row>
		<row>000100000000001000</row>
	</frame>

	<frame ms="200">
		<row>000000000000000000</row>
		<row>000000000000000000</row>
		<row>000000000000000000</row>
		<row>000000000000000000</row>
		<row>000000000000000000</row>
		<row>000000000000000000</row>
		<row>000000000000000000</row>
		<row>000000000000000000</row>
	</frame>

	<frame ms="200">
		<row>000000000000000000</row>
		<row>000000000000000000</row>
		<row>000000000000000000</row>
		<row>000000000000000000</row>
		<row>000000000000000000</row>
		<row>000000000000000000</row>
		<row>000000000000000000</row>
		<row>000000000000000000</row>
	</frame>

	<frame ms="200">
		<row>000000000000000000</row>
		<row>000000000000000000</row>
		<row>000000000000000000</row>
		<row>000000000000000000</row>
		<row>000000000000000000</row>
		<row>000000000000000000</row>
		<row>000000000000000000</row>
		<row>000000000000000000</row>
	</frame>

	<frame ms="200">
		<row>000000000000000000</row>
		<row>000000000000000000</row>
		<row>000000000000000000</row>
		<row>000000000000000000</row>
		<row>000000000000000000</row>
		<row>000000000000000000</row>
		<row>000000000000000000</row>
		<row>000000000000000000</row>
	</frame>

	<frame ms="200">
		<row>000000000000000000</row>
		<row>000000000000000000</row>
		<row>000000000000000000</row>
		<row>000000000000000000</row>
		<row>000000000000000000</row>
		<row>000000000000000000</row>
		<row>000000000000000000</row>
		<row>000000011001100000</row>
	</frame>

	<frame ms="200">
		<row>000000000000000000</row>
		<row>000000000000000000</row>
		<row>000000000000000000</row>
		<row>000000000000000000</row>
		<row>000000000000000000</row>
		<row>000000000000000000</row>
		<row>000000011001100000</row>
		<row>000001000110001000</row>
	</frame>

	<frame ms="200">
		<row>000000000000000000</row>
		<row>000000000000000000</row>
		<row>000000000000000000</row>
		<row>000000000000000000</row>
		<row>000000000000000000</row>
		<row>000000011001100000</row>
		<row>000001000110001000</row>
		<row>000001000110001000</row>
	</frame>

	<frame ms="200">
		<row>000000000000000000</row>
		<row>000000000000000000</row>
		<row>000000000000000000</row>
		<row>000000000000000000</row>
		<row>000000011001100000</row>
		<row>000001000110001000</row>
		<row>000001000110001000</row>
		<row>000000011001100000</row>
	</frame>

	<frame ms="200">
		<row>000000000000000000</row>
		<row>000000000000000000</row>
		<row>000000000000000000</row>
		<row>000000011001100000</row>
		<row>000001000110001000</row>
		<row>000001000110001000</row>
		<row>000000011001100000</row>
		<row>000000000000000000</row>
	</frame>

	<frame ms="200">
		<row>000000000000000000</row>
		<row>000000000000000000</row>
		<row>000000011001100000</row>
		<row>000001000110001000</row>
		<row>000001000110001000</row>
		<row>000000011001100000</row>
		<row>000000000000000000</row>
		<row>000000000000000000</row>
	</frame>

	<frame ms="200">
		<row>000000000000000000</row>
		<row>000000000000000000</row>
		<row>000000011001100000</row>
		<row>000001000110001000</row>
		<row>000001000110001000</row>
		<row>000000011001100000</row>
		<row>000000000000000000</row>
		<row>000000000000000000</row>
	</frame>

	<frame ms="200">
		<row>000000000000000000</row>
		<row>000000000000000000</row>
		<row>000000000000000000</row>
		<row>000000000000000000</row>
		<row>000000000000000000</row>
		<row>000000000000000000</row>
		<row>000000000000000000</row>
		<row>000000000000000000</row>
	</frame>

	<frame ms="200">
		<row>000000000000000000</row>
		<row>000000000000000000</row>
		<row>000000011001100000</row>
		<row>000001000110001000</row>
		<row>000001000110001000</row>
		<row>000000011001100000</row>
		<row>000000000000000000</row>
		<row>000000000000000000</row>
	</frame>

	<frame ms="200">
		<row>000000000000000000</row>
		<row>000000000000000000</row>
		<row>000000000000000000</row>
		<row>000000000000000000</row>
		<row>000000000000000000</row>
		<row>000000000000000000</row>
		<row>000000000000000000</row>
		<row>000000000000000000</row>
	</frame>

	<frame ms="200">
		<row>000000000000000000</row>
		<row>000000000000000000</row>
		<row>000000011001100000</row>
		<row>000001000110001000</row>
		<row>000001000110001000</row>
		<row>000000011001100000</row>
		<row>000000000000000000</row>
		<row>000000000000000000</row>
	</frame>

	<frame ms="200">
		<row>000000000000000000</row>
		<row>000000000000000000</row>
		<row>000000000000000000</row>
		<row>000000000000000000</row>
		<row>000000000000000000</row>
		<row>000000000000000000</row>
		<row>000000000000000000</row>
		<row>000000000000000000</row>
	</frame>

	<frame ms="200">
		<row>000000000000000000</row>
		<row>000000000000000000</row>
		<row>000000011001100000</row>
		<row>000001000110001000</row>
		<row>000001000110001000</row>
		<row>000000011001100000</row>
		<row>000000000000000000</row>
		<row>000000000000000000</row>
	</frame>

	<frame ms="200">
		<row>000000000000000000</row>
		<row>000000000000000000</row>
		<row>000000000000000000</row>
		<row>000000000000000000</row>
		<row>000000000000000000</row>
		<row>000000000000000000</row>
		<row>000000000000000000</row>
		<row>000000000000000000</row>
	</frame>

	<frame ms="200">
		<row>000000000000000000</row>
		<row>000000000000000000</row>
		<row>000000011001100000</row>
		<row>000001000110001000</row>
		<row>000001000110001000</row>
		<row>000000011001100000</row>
		<row>000000000000000000</row>
		<row>000000000000000000</row>
	</frame>

	<frame ms="200">
		<row>000000000000000000</row>
		<row>000000000000000000</row>
		<row>000000000000000000</row>
		<row>000000000000000000</row>
		<row>000000000000000000</row>
		<row>000000000000000000</row>
		<row>000000000000000000</row>
		<row>000000000000000000</row>
	</frame>

	<frame ms="200">
		<row>000000000000000000</row>
		<row>000000000000000000</row>
		<row>000000011001100000</row>
		<row>000001000110001000</row>
		<row>000001000110001000</row>
		<row>000000011001100000</row>
		<row>000000000000000000</row>
		<row>000000000000000000</row>
	</frame>

	<frame ms="200">
		<row>000000000000000000</row>
		<row>000000000000000000</row>
		<row>000000000000000000</row>
		<row>000000000000000000</row>
		<row>000000000000000000</row>
		<row>000000000000000000</row>
		<row>000000000000000000</row>
		<row>000000000000000000</row>
	</frame>

	<frame ms="200">
		<row>000000000000000000</row>
		<row>000000000000000000</row>
		<row>000000011001100000</row>
		<row>000001000110001000</row>
		<row>000001000110001000</row>
		<row>000000011001100000</row>
		<row>000000000000000000</row>
		<row>000000000000000000</row>
	</frame>

	<frame ms="200">
		<row>000000000000000000</row>
		<row>000000000000000000</row>
		<row>000000000000000000</row>
		<row>000000000000000000</row>
		<row>000000000000000000</row>
		<row>000000000000000000</row>
		<row>000000000000000000</row>
		<row>000000000000000000</row>
	</frame>

	<frame ms="2400">
		<row>000000000000000000</row>
		<row>000000000000000000</row>
		<row>000000011001100000</row>
		<row>000001000110001000</row>
		<row>000001000110001000</row>
		<row>000000011001100000</row>
		<row>000000000000000000</row>
		<row>000000000000000000</row>
	</frame>

	<frame ms="2400">
		<row>000000000000000000</row>
		<row>000000000000000000</row>
		<row>000000000000000000</row>
		<row>000000000000000000</row>
		<row>000000000000000000</row>
		<row>000000000000000000</row>
		<row>000000000000000000</row>
		<row>000000000000000000</row>
	</frame>

	<frame ms="2400">
		<row>000000000000000000</row>
		<row>000000000000000000</row>
		<row>000000000000000000</row>
		<row>000000000000000000</row>
		<row>000000000000000000</row>
		<row>000000000000000000</row>
		<row>000000000000000000</row>
		<row>000000000000000000</row>
	</frame>
</blm>
